<markers>
<marker lat="30.2553005219" lng="120.168899536" city="Hangzhou" region="Zhejiang" country="China" postal="None" date="11/Mar/2012:06:44:36 +0000" request="GET / HTTP/1.1" referer="&quot;-&quot;" useragent="Mozilla/4.0 (compatible; MSIE 6.0; Windows NT 5.1; SV1; .NET CLR 2.0.50727; .NET CLR 3.0.4506.2152; .NET CLR 3.5.30729; TheWorld)"/>
<marker lat="30.2553005219" lng="120.168899536" city="Hangzhou" region="Zhejiang" country="China" postal="None" date="11/Mar/2012:06:44:37 +0000" request="GET /stylesheets/base.css HTTP/1.1" referer="&quot;http://semjy.com/&quot;" useragent="Mozilla/4.0 (compatible; MSIE 6.0; Windows NT 5.1; SV1; .NET CLR 2.0.50727; .NET CLR 3.0.4506.2152; .NET CLR 3.5.30729; TheWorld)"/>
<marker lat="30.2553005219" lng="120.168899536" city="Hangzhou" region="Zhejiang" country="China" postal="None" date="11/Mar/2012:06:44:37 +0000" request="GET /stylesheets/skeleton.css HTTP/1.1" referer="&quot;http://semjy.com/&quot;" useragent="Mozilla/4.0 (compatible; MSIE 6.0; Windows NT 5.1; SV1; .NET CLR 2.0.50727; .NET CLR 3.0.4506.2152; .NET CLR 3.5.30729; TheWorld)"/>
<marker lat="30.2553005219" lng="120.168899536" city="Hangzhou" region="Zhejiang" country="China" postal="None" date="11/Mar/2012:06:44:37 +0000" request="GET /stylesheets/layout.css HTTP/1.1" referer="&quot;http://semjy.com/&quot;" useragent="Mozilla/4.0 (compatible; MSIE 6.0; Windows NT 5.1; SV1; .NET CLR 2.0.50727; .NET CLR 3.0.4506.2152; .NET CLR 3.5.30729; TheWorld)"/>
<marker lat="30.2553005219" lng="120.168899536" city="Hangzhou" region="Zhejiang" country="China" postal="None" date="11/Mar/2012:06:44:38 +0000" request="GET /stylesheets/custom.css HTTP/1.1" referer="&quot;http://semjy.com/&quot;" useragent="Mozilla/4.0 (compatible; MSIE 6.0; Windows NT 5.1; SV1; .NET CLR 2.0.50727; .NET CLR 3.0.4506.2152; .NET CLR 3.5.30729; TheWorld)"/>
<marker lat="30.2553005219" lng="120.168899536" city="Hangzhou" region="Zhejiang" country="China" postal="None" date="11/Mar/2012:06:44:39 +0000" request="GET /javascripts/tabs.js HTTP/1.1" referer="&quot;http://semjy.com/&quot;" useragent="Mozilla/4.0 (compatible; MSIE 6.0; Windows NT 5.1; SV1; .NET CLR 2.0.50727; .NET CLR 3.0.4506.2152; .NET CLR 3.5.30729; TheWorld)"/>
<marker lat="30.2553005219" lng="120.168899536" city="Hangzhou" region="Zhejiang" country="China" postal="None" date="11/Mar/2012:06:44:38 +0000" request="GET /images/me.png HTTP/1.1" referer="&quot;http://semjy.com/&quot;" useragent="Mozilla/4.0 (compatible; MSIE 6.0; Windows NT 5.1; SV1; .NET CLR 2.0.50727; .NET CLR 3.0.4506.2152; .NET CLR 3.5.30729; TheWorld)"/>
<marker lat="30.2553005219" lng="120.168899536" city="Hangzhou" region="Zhejiang" country="China" postal="None" date="11/Mar/2012:06:44:47 +0000" request="GET / HTTP/1.1" referer="&quot;-&quot;" useragent="Mozilla/4.0 (compatible; MSIE 6.0; Windows NT 5.1; SV1; .NET CLR 2.0.50727; .NET CLR 3.0.4506.2152; .NET CLR 3.5.30729; TheWorld)"/>
<marker lat="30.2553005219" lng="120.168899536" city="Hangzhou" region="Zhejiang" country="China" postal="None" date="11/Mar/2012:06:44:47 +0000" request="GET /stylesheets/base.css HTTP/1.1" referer="&quot;http://www.semjy.com/&quot;" useragent="Mozilla/4.0 (compatible; MSIE 6.0; Windows NT 5.1; SV1; .NET CLR 2.0.50727; .NET CLR 3.0.4506.2152; .NET CLR 3.5.30729; TheWorld)"/>
<marker lat="30.2553005219" lng="120.168899536" city="Hangzhou" region="Zhejiang" country="China" postal="None" date="11/Mar/2012:06:44:47 +0000" request="GET /stylesheets/skeleton.css HTTP/1.1" referer="&quot;http://www.semjy.com/&quot;" useragent="Mozilla/4.0 (compatible; MSIE 6.0; Windows NT 5.1; SV1; .NET CLR 2.0.50727; .NET CLR 3.0.4506.2152; .NET CLR 3.5.30729; TheWorld)"/>
<marker lat="30.2553005219" lng="120.168899536" city="Hangzhou" region="Zhejiang" country="China" postal="None" date="11/Mar/2012:06:44:48 +0000" request="GET /stylesheets/layout.css HTTP/1.1" referer="&quot;http://www.semjy.com/&quot;" useragent="Mozilla/4.0 (compatible; MSIE 6.0; Windows NT 5.1; SV1; .NET CLR 2.0.50727; .NET CLR 3.0.4506.2152; .NET CLR 3.5.30729; TheWorld)"/>
<marker lat="30.2553005219" lng="120.168899536" city="Hangzhou" region="Zhejiang" country="China" postal="None" date="11/Mar/2012:06:44:48 +0000" request="GET /stylesheets/custom.css HTTP/1.1" referer="&quot;http://www.semjy.com/&quot;" useragent="Mozilla/4.0 (compatible; MSIE 6.0; Windows NT 5.1; SV1; .NET CLR 2.0.50727; .NET CLR 3.0.4506.2152; .NET CLR 3.5.30729; TheWorld)"/>
<marker lat="30.2553005219" lng="120.168899536" city="Hangzhou" region="Zhejiang" country="China" postal="None" date="11/Mar/2012:06:44:49 +0000" request="GET /javascripts/tabs.js HTTP/1.1" referer="&quot;http://www.semjy.com/&quot;" useragent="Mozilla/4.0 (compatible; MSIE 6.0; Windows NT 5.1; SV1; .NET CLR 2.0.50727; .NET CLR 3.0.4506.2152; .NET CLR 3.5.30729; TheWorld)"/>
<marker lat="30.2553005219" lng="120.168899536" city="Hangzhou" region="Zhejiang" country="China" postal="None" date="11/Mar/2012:06:44:49 +0000" request="GET /images/me.png HTTP/1.1" referer="&quot;http://www.semjy.com/&quot;" useragent="Mozilla/4.0 (compatible; MSIE 6.0; Windows NT 5.1; SV1; .NET CLR 2.0.50727; .NET CLR 3.0.4506.2152; .NET CLR 3.5.30729; TheWorld)"/>
<marker lat="23.1166992188" lng="113.25" city="Guangzhou" region="Guangdong" country="China" postal="None" date="11/Mar/2012:07:55:30 +0000" request="GET / HTTP/1.0" referer="&quot;-&quot;" useragent="Mozilla/4.0 (compatible; MSIE 6.0; Windows NT 5.1; SV1; .NET CLR 1.1.4322;TencentTraveler)"/>
<marker lat="31.0049991608" lng="121.408599854" city="Shanghai" region="Shanghai" country="China" postal="None" date="11/Mar/2012:08:12:46 +0000" request="GET / HTTP/1.0" referer="&quot;-&quot;" useragent="Mozilla/4.0 (compatible; MSIE 6.0; Windows NT 5.1; SV1; .NET CLR 1.1.4322;TencentTraveler)"/>
<marker lat="38.0" lng="-97.0" city="None" region="None" country="United States" postal="None" date="11/Mar/2012:08:19:06 +0000" request="GET / HTTP/1.1" referer="&quot;-&quot;" useragent="Mozilla/4.0 (compatible; MSIE 6.0; Windows NT 5.1)"/>
<marker lat="34.0415992737" lng="-118.298797607" city="Los Angeles" region="California" country="United States" postal="None" date="11/Mar/2012:11:00:57 +0000" request="GET / HTTP/1.1" referer="&quot;-&quot;" useragent="Mozilla/5.0 (Macintosh; Intel Mac OS X 10_7_3) AppleWebKit/535.19 (KHTML, like Gecko) Chrome/18.0.1025.45 Safari/535.19"/>
<marker lat="53.25" lng="10.3999996185" city="Lneburg" region="Niedersachsen" country="Germany" postal="None" date="11/Mar/2012:12:32:49 +0000" request="GET / HTTP/1.1" referer="&quot;-&quot;" useragent="Mozilla/5.0 (iPad; CPU OS 5_1 like Mac OS X) AppleWebKit/534.46 (KHTML, like Gecko) Version/5.1 Mobile/9B176 Safari/7534.48.3"/>
<marker lat="40.3499984741" lng="0.416700005531" city="Pescola" region="Comunidad Valenciana" country="Spain" postal="None" date="11/Mar/2012:16:30:47 +0000" request="GET / HTTP/1.1" referer="&quot;http://www.kickstarter.com/projects/1650920829/nimbus?ref=card&quot;" useragent="Mozilla/5.0 (Macintosh; Intel Mac OS X 10_7_3) AppleWebKit/535.11 (KHTML, like Gecko) Chrome/17.0.963.79 Safari/535.11"/>
<marker lat="23.1166992188" lng="113.25" city="Guangzhou" region="Guangdong" country="China" postal="None" date="11/Mar/2012:16:36:49 +0000" request="GET / HTTP/1.1" referer="&quot;-&quot;" useragent="Mozilla/4.0 (compatible; MSIE 6.0; Windows NT 5.1)"/>
<marker lat="23.1166992188" lng="113.25" city="Guangzhou" region="Guangdong" country="China" postal="None" date="11/Mar/2012:17:37:46 +0000" request="GET / HTTP/1.1" referer="&quot;-&quot;" useragent="Mozilla/4.0 (compatible; MSIE 6.0; Windows NT 5.1)"/>
<marker lat="23.1166992188" lng="113.25" city="Guangzhou" region="Guangdong" country="China" postal="None" date="11/Mar/2012:20:06:14 +0000" request="GET / HTTP/1.1" referer="&quot;-&quot;" useragent="Mozilla/4.0 (compatible; MSIE 6.0; Windows NT 5.1)"/>
<marker lat="42.7592010498" lng="-83.4111022949" city="Clarkston" region="Michigan" country="United States" postal="48348" date="11/Mar/2012:21:28:49 +0000" request="GET / HTTP/1.1" referer="&quot;http://www.kickstarter.com/projects/1650920829/nimbus?ref=card&quot;" useragent="Mozilla/5.0 (Macintosh; Intel Mac OS X 10_7_3) AppleWebKit/535.11 (KHTML, like Gecko) Chrome/17.0.963.78 Safari/535.11"/>
<marker lat="23.1166992188" lng="113.25" city="Guangzhou" region="Guangdong" country="China" postal="None" date="11/Mar/2012:22:24:43 +0000" request="GET / HTTP/1.0" referer="&quot;-&quot;" useragent="Mozilla/4.0 (compatible; MSIE 6.0; Windows NT 5.1; SV1; .NET CLR 1.1.4322;TencentTraveler)"/>
<marker lat="23.1166992188" lng="113.25" city="Guangzhou" region="Guangdong" country="China" postal="None" date="11/Mar/2012:23:13:10 +0000" request="GET / HTTP/1.0" referer="&quot;-&quot;" useragent="Mozilla/4.0 (compatible; MSIE 6.0; Windows NT 5.1; SV1; .NET CLR 1.1.4322;TencentTraveler)"/>
<marker lat="31.0049991608" lng="121.408599854" city="Shanghai" region="Shanghai" country="China" postal="None" date="11/Mar/2012:23:19:12 +0000" request="GET / HTTP/1.1" referer="&quot;-&quot;" useragent="Mozilla/4.0 (compatible; MSIE 6.0; Windows NT 5.1)"/>
<marker lat="31.0049991608" lng="121.408599854" city="Shanghai" region="Shanghai" country="China" postal="None" date="12/Mar/2012:00:03:13 +0000" request="GET / HTTP/1.0" referer="&quot;-&quot;" useragent="Mozilla/4.0 (compatible; MSIE 6.0; Windows NT 5.1; SV1; .NET CLR 1.1.4322;TencentTraveler)"/>
<marker lat="39.9289016724" lng="116.388298035" city="Beijing" region="Beijing" country="China" postal="None" date="12/Mar/2012:00:18:47 +0000" request="HEAD / HTTP/1.0" referer="&quot;-&quot;" useragent="-"/>
<marker lat="31.0049991608" lng="121.408599854" city="Shanghai" region="Shanghai" country="China" postal="None" date="12/Mar/2012:00:24:53 +0000" request="GET / HTTP/1.0" referer="&quot;-&quot;" useragent="Mozilla/4.0 (compatible; MSIE 6.0; Windows NT 5.1; SV1; .NET CLR 1.1.4322;TencentTraveler)"/>
<marker lat="31.0049991608" lng="121.408599854" city="Shanghai" region="Shanghai" country="China" postal="None" date="12/Mar/2012:01:29:48 +0000" request="GET / HTTP/1.1" referer="&quot;-&quot;" useragent="Mozilla/4.0 (compatible; MSIE 6.0; Windows NT 5.1)"/>
<marker lat="31.0049991608" lng="121.408599854" city="Shanghai" region="Shanghai" country="China" postal="None" date="12/Mar/2012:01:43:48 +0000" request="HEAD / HTTP/1.0" referer="&quot;-&quot;" useragent="-"/>
<marker lat="33.095199585" lng="-96.7524032593" city="Plano" region="Texas" country="United States" postal="75025" date="12/Mar/2012:06:30:04 +0000" request="GET / HTTP/1.1" referer="&quot;http://www.kickstarter.com/projects/1650920829/nimbus&quot;" useragent="Mozilla/5.0 (Windows NT 6.0; rv:10.0.2) Gecko/20100101 Firefox/10.0.2"/>
<marker lat="33.095199585" lng="-96.7524032593" city="Plano" region="Texas" country="United States" postal="75025" date="12/Mar/2012:06:30:04 +0000" request="GET /stylesheets/base.css HTTP/1.1" referer="&quot;-&quot;" useragent="Mozilla/4.0 (compatible;)"/>
<marker lat="33.095199585" lng="-96.7524032593" city="Plano" region="Texas" country="United States" postal="75025" date="12/Mar/2012:06:30:04 +0000" request="GET /images/apple-touch-icon-114x114.png HTTP/1.1" referer="&quot;-&quot;" useragent="Mozilla/4.0 (compatible;)"/>
<marker lat="33.095199585" lng="-96.7524032593" city="Plano" region="Texas" country="United States" postal="75025" date="12/Mar/2012:06:30:04 +0000" request="GET /stylesheets/custom.css HTTP/1.1" referer="&quot;-&quot;" useragent="Mozilla/4.0 (compatible;)"/>
<marker lat="33.095199585" lng="-96.7524032593" city="Plano" region="Texas" country="United States" postal="75025" date="12/Mar/2012:06:30:04 +0000" request="GET /images/apple-touch-icon.png HTTP/1.1" referer="&quot;-&quot;" useragent="Mozilla/4.0 (compatible;)"/>
<marker lat="33.095199585" lng="-96.7524032593" city="Plano" region="Texas" country="United States" postal="75025" date="12/Mar/2012:06:30:04 +0000" request="GET /stylesheets/skeleton.css HTTP/1.1" referer="&quot;-&quot;" useragent="Mozilla/4.0 (compatible;)"/>
<marker lat="33.095199585" lng="-96.7524032593" city="Plano" region="Texas" country="United States" postal="75025" date="12/Mar/2012:06:30:04 +0000" request="GET /stylesheets/layout.css HTTP/1.1" referer="&quot;-&quot;" useragent="Mozilla/4.0 (compatible;)"/>
<marker lat="33.095199585" lng="-96.7524032593" city="Plano" region="Texas" country="United States" postal="75025" date="12/Mar/2012:06:30:04 +0000" request="GET /images/apple-touch-icon-72x72.png HTTP/1.1" referer="&quot;-&quot;" useragent="Mozilla/4.0 (compatible;)"/>
<marker lat="33.095199585" lng="-96.7524032593" city="Plano" region="Texas" country="United States" postal="75025" date="12/Mar/2012:06:30:04 +0000" request="GET /javascripts/tabs.js HTTP/1.1" referer="&quot;-&quot;" useragent="Mozilla/4.0 (compatible;)"/>
<marker lat="33.095199585" lng="-96.7524032593" city="Plano" region="Texas" country="United States" postal="75025" date="12/Mar/2012:06:30:04 +0000" request="GET /images/me.png HTTP/1.1" referer="&quot;-&quot;" useragent="Mozilla/4.0 (compatible;)"/>
<marker lat="31.0049991608" lng="121.408599854" city="Shanghai" region="Shanghai" country="China" postal="None" date="12/Mar/2012:08:05:26 +0000" request="GET / HTTP/1.0" referer="&quot;-&quot;" useragent="Mozilla/4.0 (compatible; MSIE 6.0; Windows NT 5.1; SV1; .NET CLR 1.1.4322;TencentTraveler)"/>
<marker lat="23.1166992188" lng="113.25" city="Guangzhou" region="Guangdong" country="China" postal="None" date="12/Mar/2012:09:01:43 +0000" request="GET / HTTP/1.0" referer="&quot;-&quot;" useragent="Mozilla/4.0 (compatible; MSIE 6.0; Windows NT 5.1; SV1; .NET CLR 1.1.4322;TencentTraveler)"/>
<marker lat="23.1166992188" lng="113.25" city="Guangzhou" region="Guangdong" country="China" postal="None" date="12/Mar/2012:09:04:58 +0000" request="GET / HTTP/1.0" referer="&quot;-&quot;" useragent="Mozilla/4.0 (compatible; MSIE 6.0; Windows NT 5.1; SV1; .NET CLR 1.1.4322;TencentTraveler)"/>
<marker lat="31.0049991608" lng="121.408599854" city="Shanghai" region="Shanghai" country="China" postal="None" date="12/Mar/2012:09:15:47 +0000" request="GET / HTTP/1.0" referer="&quot;-&quot;" useragent="Mozilla/4.0 (compatible; MSIE 6.0; Windows NT 5.1; SV1; .NET CLR 1.1.4322;TencentTraveler)"/>
<marker lat="38.0" lng="-97.0" city="None" region="None" country="United States" postal="None" date="12/Mar/2012:12:26:51 +0000" request="GET / HTTP/1.1" referer="&quot;-&quot;" useragent="Mozilla/5.0 (X11; U; Linux i686; en-US; rv:1.9.2.24; ips-agent) Gecko/20111107 Ubuntu/10.04 (lucid) Firefox/3.6.24"/>
<marker lat="38.0" lng="-97.0" city="None" region="None" country="United States" postal="None" date="12/Mar/2012:12:28:29 +0000" request="GET / HTTP/1.1" referer="&quot;-&quot;" useragent="Mozilla/5.0 (X11; U; Linux i686; en-US; rv:1.9.2.24; ips-agent) Gecko/20111107 Ubuntu/10.04 (lucid) Firefox/3.6.24"/>
<marker lat="38.0" lng="-97.0" city="None" region="None" country="United States" postal="None" date="12/Mar/2012:12:29:20 +0000" request="GET /index.html HTTP/1.1" referer="&quot;-&quot;" useragent="BlackBerry9630/5.0.0.732 Profile/MIDP-2.1 Configuration/CLDC-1.1 VendorID/102 ips-agent"/>
<marker lat="38.0" lng="-97.0" city="None" region="None" country="United States" postal="None" date="12/Mar/2012:12:30:10 +0000" request="GET /resume.html HTTP/1.1" referer="&quot;-&quot;" useragent="Mozilla/5.0 (X11; U; Linux i686; en-US; rv:1.9.2.24; ips-agent) Gecko/20111107 Ubuntu/10.04 (lucid) Firefox/3.6.24"/>
<marker lat="38.0" lng="-97.0" city="None" region="None" country="United States" postal="None" date="12/Mar/2012:12:59:02 +0000" request="GET /resume.html HTTP/1.1" referer="&quot;http://search.yahoo.com/search?n=100&amp;ei=UTF-8&amp;va_vt=any&amp;vo_vt=any&amp;ve_vt=any&amp;vp_vt=any&amp;vd=all&amp;vst=0&amp;vf=all&amp;vc=us&amp;vm=r&amp;fl=1&amp;vl=lang_en&amp;fr=ush-&amp;p=%22resume.html%22+%22Intel+Corporation%22+-sample+-example+-template+-job+-SUBMIT+-Applicant++JAVA&amp;vs=&quot;" useragent="Mozilla/4.0 (compatible; MSIE 8.0; Windows NT 6.1; SV1; .NET CLR 2.0.50727)"/>
<marker lat="38.0" lng="-97.0" city="None" region="None" country="United States" postal="None" date="12/Mar/2012:13:05:01 +0000" request="HEAD / HTTP/1.0" referer="&quot;-&quot;" useragent="-"/>
<marker lat="39.9289016724" lng="116.388298035" city="Beijing" region="Beijing" country="China" postal="None" date="12/Mar/2012:16:33:10 +0000" request="GET / HTTP/1.1" referer="&quot;http://www.hangzhoutongzhi.com/&quot;" useragent="Mozilla/4.0 (compatible; MSIE 6.0; Windows NT 5.1)"/>
<marker lat="36.3596992493" lng="-119.315498352" city="Visalia" region="California" country="United States" postal="None" date="12/Mar/2012:18:27:26 +0000" request="GET / HTTP/1.1" referer="&quot;-&quot;" useragent="Mozilla/5.0 (Macintosh; Intel Mac OS X 10_7_3) AppleWebKit/535.19 (KHTML, like Gecko) Chrome/18.0.1025.54 Safari/535.19"/>
<marker lat="52.2000007629" lng="0.116700001061" city="Cambridge" region="Cambridgeshire" country="United Kingdom" postal="None" date="12/Mar/2012:19:29:23 +0000" request="GET / HTTP/1.1" referer="&quot;http://www.kickstarter.com/projects/1650920829/nimbus?ref=card&quot;" useragent="Mozilla/5.0 (Macintosh; Intel Mac OS X 10_7_3) AppleWebKit/535.11 (KHTML, like Gecko) Chrome/17.0.963.78 Safari/535.11"/>
<marker lat="59.5332984924" lng="18.0832996368" city="Vallentuna" region="Stockholms Lan" country="Sweden" postal="None" date="12/Mar/2012:20:49:50 +0000" request="GET / HTTP/1.1" referer="&quot;-&quot;" useragent="Mozilla/5.0 (Macintosh; Intel Mac OS X 10_7_3) AppleWebKit/534.53.11 (KHTML, like Gecko) Version/5.1.3 Safari/534.53.10"/>
<marker lat="40.7605018616" lng="-73.9933013916" city="New York" region="New York" country="United States" postal="10036" date="12/Mar/2012:20:51:47 +0000" request="GET / HTTP/1.1" referer="&quot;http://www.kickstarter.com/projects/1650920829/nimbus&quot;" useragent="Mozilla/5.0 (Windows; U; Windows NT 5.1; en-US; rv:1.9.2.26) Gecko/2012021505 Firefox/3.6.26ms1"/>
<marker lat="44.0999984741" lng="10.3999996185" city="Castelnuovo Di Garfagnana" region="Toscana" country="Italy" postal="None" date="12/Mar/2012:20:57:49 +0000" request="GET / HTTP/1.1" referer="&quot;http://www.kickstarter.com/projects/1650920829/nimbus?ref=card&quot;" useragent="Mozilla/5.0 (Windows NT 6.1; WOW64; rv:10.0.2) Gecko/20100101 Firefox/10.0.2"/>
<marker lat="54.0993995667" lng="22.9330997467" city="Suwalki" region="Podlaskie" country="Poland" postal="None" date="12/Mar/2012:21:37:23 +0000" request="GET / HTTP/1.1" referer="&quot;http://www.kickstarter.com/projects/1650920829/nimbus&quot;" useragent="Mozilla/5.0 (hp-tablet; Linux; hpwOS/3.0.5; U; en-US) AppleWebKit/534.6 (KHTML, like Gecko) wOSBrowser/234.83 Safari/534.6 TouchPad/1.0"/>
<marker lat="39.9289016724" lng="116.388298035" city="Beijing" region="Beijing" country="China" postal="None" date="12/Mar/2012:21:38:06 +0000" request="GET / HTTP/1.1" referer="&quot;-&quot;" useragent="Mozilla/5.0 (Windows NT 5.1; rv:6.0.2) Gecko/20100101 Firefox/6.0.2"/>
<marker lat="39.9289016724" lng="116.388298035" city="Beijing" region="Beijing" country="China" postal="None" date="12/Mar/2012:21:38:06 +0000" request="GET / HTTP/1.1" referer="&quot;-&quot;" useragent="Mozilla/5.0 (Windows NT 5.1; rv:6.0.2) Gecko/20100101 Firefox/6.0.2"/>
<marker lat="31.0049991608" lng="121.408599854" city="Shanghai" region="Shanghai" country="China" postal="None" date="12/Mar/2012:23:06:48 +0000" request="GET / HTTP/1.0" referer="&quot;-&quot;" useragent="Mozilla/4.0 (compatible; MSIE 6.0; Windows NT 5.1; SV1; .NET CLR 1.1.4322;TencentTraveler)"/>
<marker lat="23.1166992188" lng="113.25" city="Guangzhou" region="Guangdong" country="China" postal="None" date="12/Mar/2012:23:22:10 +0000" request="GET / HTTP/1.0" referer="&quot;-&quot;" useragent="Mozilla/4.0 (compatible; MSIE 6.0; Windows NT 5.1; SV1; .NET CLR 1.1.4322;TencentTraveler)"/>
<marker lat="-2.51670002937" lng="-44.2667007446" city="So Lus" region="Maranhao" country="Brazil" postal="None" date="12/Mar/2012:23:36:24 +0000" request="GET / HTTP/1.0" referer="&quot;http://www.kickstarter.com/projects/1650920829/nimbus?ref=category&quot;" useragent="Mozilla/5.0 (Windows NT 5.1) AppleWebKit/535.11 (KHTML, like Gecko) Chrome/17.0.963.79 Safari/535.11"/>
<marker lat="23.1166992188" lng="113.25" city="Guangzhou" region="Guangdong" country="China" postal="None" date="13/Mar/2012:00:07:37 +0000" request="GET / HTTP/1.0" referer="&quot;-&quot;" useragent="Mozilla/4.0 (compatible; MSIE 6.0; Windows NT 5.1; SV1; .NET CLR 1.1.4322;TencentTraveler)"/>
<marker lat="31.0049991608" lng="121.408599854" city="Shanghai" region="Shanghai" country="China" postal="None" date="13/Mar/2012:00:23:15 +0000" request="GET / HTTP/1.0" referer="&quot;-&quot;" useragent="Mozilla/4.0 (compatible; MSIE 6.0; Windows NT 5.1; SV1; .NET CLR 1.1.4322;TencentTraveler)"/>
<marker lat="38.0" lng="-97.0" city="None" region="None" country="United States" postal="None" date="13/Mar/2012:00:47:57 +0000" request="GET / HTTP/1.1" referer="&quot;-&quot;" useragent="Python-urllib/2.4"/>
<marker lat="23.1166992188" lng="113.25" city="Guangzhou" region="Guangdong" country="China" postal="None" date="13/Mar/2012:02:10:34 +0000" request="GET / HTTP/1.1" referer="&quot;-&quot;" useragent="Mozilla/4.0 (compatible; MSIE 6.0; Windows NT 5.1)"/>
<marker lat="37.7484016418" lng="-122.415603638" city="San Francisco" region="California" country="United States" postal="94110" date="13/Mar/2012:04:00:00 +0000" request="GET / HTTP/1.1" referer="&quot;-&quot;" useragent="Mozilla/5.0 (Windows NT 5.1) AppleWebKit/535.11 (KHTML, like Gecko) Chrome/17.0.963.78 Safari/535.11"/>
<marker lat="36.3596992493" lng="-119.315498352" city="Visalia" region="California" country="United States" postal="None" date="13/Mar/2012:05:07:18 +0000" request="GET / HTTP/1.1" referer="&quot;-&quot;" useragent="Mozilla/5.0 (Macintosh; Intel Mac OS X 10_7_3) AppleWebKit/535.19 (KHTML, like Gecko) Chrome/18.0.1025.54 Safari/535.19"/>
<marker lat="38.0" lng="-97.0" city="None" region="None" country="United States" postal="None" date="13/Mar/2012:06:22:04 +0000" request="GET / HTTP/1.1" referer="&quot;-&quot;" useragent="Mozilla/5.0 (Windows; U; Windows NT 6.0; en-US; rv:1.9.2.3) Gecko/20100401 Firefox/3.6.3 GTB6 (.NET CLR 3.5.30729)"/>
<marker lat="38.9345016479" lng="-77.0596008301" city="Washington" region="District of Columbia" country="United States" postal="20008" date="13/Mar/2012:06:33:24 +0000" request="GET / HTTP/1.1" referer="&quot;-&quot;" useragent="Mozilla/4.0 (compatible; MSIE 7.0; Windows NT 5.2)"/>
<marker lat="38.9345016479" lng="-77.0596008301" city="Washington" region="District of Columbia" country="United States" postal="20008" date="13/Mar/2012:06:33:30 +0000" request="GET /stylesheets/custom.css HTTP/1.1" referer="&quot;-&quot;" useragent="Mozilla/4.0 (compatible; MSIE 7.0; Windows NT 5.2)"/>
<marker lat="38.9345016479" lng="-77.0596008301" city="Washington" region="District of Columbia" country="United States" postal="20008" date="13/Mar/2012:06:33:30 +0000" request="GET /resume.html HTTP/1.1" referer="&quot;-&quot;" useragent="Mozilla/4.0 (compatible; MSIE 7.0; Windows NT 5.2)"/>
<marker lat="38.9345016479" lng="-77.0596008301" city="Washington" region="District of Columbia" country="United States" postal="20008" date="13/Mar/2012:06:33:34 +0000" request="GET /index.html HTTP/1.1" referer="&quot;-&quot;" useragent="Mozilla/4.0 (compatible; MSIE 7.0; Windows NT 5.2)"/>
<marker lat="38.9345016479" lng="-77.0596008301" city="Washington" region="District of Columbia" country="United States" postal="20008" date="13/Mar/2012:06:33:36 +0000" request="GET /stylesheets/layout.css HTTP/1.1" referer="&quot;-&quot;" useragent="Mozilla/4.0 (compatible; MSIE 7.0; Windows NT 5.2)"/>
<marker lat="38.9345016479" lng="-77.0596008301" city="Washington" region="District of Columbia" country="United States" postal="20008" date="13/Mar/2012:06:33:39 +0000" request="GET /stylesheets/base.css HTTP/1.1" referer="&quot;-&quot;" useragent="Mozilla/4.0 (compatible; MSIE 7.0; Windows NT 5.2)"/>
<marker lat="38.9345016479" lng="-77.0596008301" city="Washington" region="District of Columbia" country="United States" postal="20008" date="13/Mar/2012:06:33:41 +0000" request="GET /stylesheets/skeleton.css HTTP/1.1" referer="&quot;-&quot;" useragent="Mozilla/4.0 (compatible; MSIE 7.0; Windows NT 5.2)"/>
<marker lat="39.9289016724" lng="116.388298035" city="Beijing" region="Beijing" country="China" postal="None" date="13/Mar/2012:07:48:10 +0000" request="GET / HTTP/1.1" referer="&quot;http://www.hangzhoutongzhi.com/&quot;" useragent="Mozilla/4.0 (compatible; MSIE 6.0; Windows NT 5.1)"/>
<marker lat="24.8047008514" lng="120.9713974" city="Hsinchu" region="T'ai-wan" country="Taiwan" postal="None" date="13/Mar/2012:07:58:42 +0000" request="GET / HTTP/1.1" referer="&quot;-&quot;" useragent="-"/>
<marker lat="23.1166992188" lng="113.25" city="Guangzhou" region="Guangdong" country="China" postal="None" date="13/Mar/2012:08:09:44 +0000" request="GET / HTTP/1.0" referer="&quot;-&quot;" useragent="Mozilla/4.0 (compatible; MSIE 6.0; Windows NT 5.1; SV1; .NET CLR 1.1.4322;TencentTraveler)"/>
<marker lat="23.1166992188" lng="113.25" city="Guangzhou" region="Guangdong" country="China" postal="None" date="13/Mar/2012:08:23:13 +0000" request="GET / HTTP/1.0" referer="&quot;-&quot;" useragent="Mozilla/4.0 (compatible; MSIE 6.0; Windows NT 5.1; SV1; .NET CLR 1.1.4322;TencentTraveler)"/>
<marker lat="31.0049991608" lng="121.408599854" city="Shanghai" region="Shanghai" country="China" postal="None" date="13/Mar/2012:09:15:42 +0000" request="GET / HTTP/1.0" referer="&quot;-&quot;" useragent="Mozilla/4.0 (compatible; MSIE 6.0; Windows NT 5.1; SV1; .NET CLR 1.1.4322;TencentTraveler)"/>
<marker lat="38.0" lng="-97.0" city="None" region="None" country="United States" postal="None" date="13/Mar/2012:09:56:24 +0000" request="GET /resume.html HTTP/1.1" referer="&quot;http://search.yahoo.com/search?n=100&amp;ei=UTF-8&amp;va_vt=any&amp;vo_vt=any&amp;ve_vt=any&amp;vp_vt=any&amp;vd=y&amp;vst=0&amp;vf=all&amp;vc=us&amp;vm=r&amp;fl=1&amp;vl=lang_en&amp;fr=ush-&amp;p=%22resume.html%22+%22Intel+Corporation%22+-sample+-example+-template+-job+-SUBMIT+-Applicant+&amp;vs=&quot;" useragent="Mozilla/4.0 (compatible; MSIE 8.0; Windows NT 6.1; SV1; .NET CLR 2.0.50727)"/>
<marker lat="12.983300209" lng="77.5832977295" city="Bangalore" region="Karnataka" country="India" postal="None" date="13/Mar/2012:10:19:16 +0000" request="GET / HTTP/1.1" referer="&quot;http://www.kickstarter.com/projects/1650920829/nimbus&quot;" useragent="Mozilla/5.0 (Windows NT 6.1; WOW64) AppleWebKit/535.11 (KHTML, like Gecko) Chrome/17.0.963.78 Safari/535.11"/>
<marker lat="3.58330011368" lng="98.6667022705" city="Medan" region="Sumatera Utara" country="Indonesia" postal="None" date="13/Mar/2012:11:59:57 +0000" request="GET / HTTP/1.1" referer="&quot;http://www.kickstarter.com/projects/1650920829/nimbus?ref=card&quot;" useragent="Mozilla/5.0 (Windows NT 5.1) AppleWebKit/535.11 (KHTML, like Gecko) Chrome/17.0.963.79 Safari/535.11"/>
<marker lat="45.4667015076" lng="9.19999980927" city="Milan" region="Lombardia" country="Italy" postal="None" date="13/Mar/2012:12:00:16 +0000" request="GET / HTTP/1.1" referer="&quot;-&quot;" useragent="Mozilla/5.0 (Macintosh; Intel Mac OS X 10_7_3) AppleWebKit/534.53.11 (KHTML, like Gecko) Version/5.1.3 Safari/534.53.10"/>
<marker lat="44.5428009033" lng="18.6693992615" city="Tuzla" region="Federation of Bosnia and Herzegovina" country="Bosnia and Herzegovina" postal="None" date="13/Mar/2012:15:41:24 +0000" request="GET / HTTP/1.1" referer="&quot;http://www.kickstarter.com/projects/1650920829/nimbus&quot;" useragent="Mozilla/5.0 (Macintosh; Intel Mac OS X 10.7; rv:11.0) Gecko/20100101 Firefox/11.0"/>
<marker lat="38.0" lng="-97.0" city="None" region="None" country="United States" postal="None" date="13/Mar/2012:16:15:27 +0000" request="GET / HTTP/1.0" referer="&quot;-&quot;" useragent="Mozilla/5.0 (X11; U; Linux i686; en-US; rv:1.7.5) Gecko/20041107 Firefox/1.0"/>
<marker lat="51.5001983643" lng="-0.126200005412" city="London" region="London, City of" country="United Kingdom" postal="None" date="13/Mar/2012:16:59:13 +0000" request="GET / HTTP/1.1" referer="&quot;http://www.kickstarter.com/projects/1650920829/nimbus?ref=card&quot;" useragent="Mozilla/5.0 (Macintosh; Intel Mac OS X 10_6_8) AppleWebKit/535.11 (KHTML, like Gecko) Chrome/17.0.963.79 Safari/535.11"/>
<marker lat="39.9289016724" lng="116.388298035" city="Beijing" region="Beijing" country="China" postal="None" date="13/Mar/2012:17:30:51 +0000" request="GET / HTTP/1.1" referer="&quot;-&quot;" useragent="Mozilla/5.0 (Windows NT 5.1; rv:6.0.2) Gecko/20100101 Firefox/6.0.2"/>
<marker lat="39.9289016724" lng="116.388298035" city="Beijing" region="Beijing" country="China" postal="None" date="13/Mar/2012:17:30:51 +0000" request="GET / HTTP/1.1" referer="&quot;-&quot;" useragent="Mozilla/5.0 (Windows NT 5.1; rv:6.0.2) Gecko/20100101 Firefox/6.0.2"/>
<marker lat="24.8047008514" lng="120.9713974" city="Hsinchu" region="T'ai-wan" country="Taiwan" postal="None" date="13/Mar/2012:18:27:02 +0000" request="GET / HTTP/1.1" referer="&quot;-&quot;" useragent="-"/>
<marker lat="38.0" lng="-97.0" city="None" region="None" country="United States" postal="None" date="13/Mar/2012:20:43:21 +0000" request="GET /resume.html HTTP/1.0" referer="&quot;http://search.yahoo.com/search?n=100&amp;ei=UTF-8&amp;va_vt=any&amp;vo_vt=any&amp;ve_vt=any&amp;vp_vt=any&amp;vd=y&amp;vst=0&amp;vf=all&amp;vc=us&amp;vm=r&amp;fl=1&amp;vl=lang_en&amp;fr=ush-&amp;p=%22resume.html%22+%22Intel+Corporation%22+-sample+-example+-template+-job+-SUBMIT+-Applicant++and+-xerox+-ADP+-POS+-%22Point+of+Sale%22+-%22payroll+systems%22&amp;vs=&quot;" useragent="Mozilla/4.0 (compatible; MSIE 8.0; Windows NT 6.1; SV1; .NET CLR 2.0.50727)"/>
<marker lat="29.7754993439" lng="-95.4151992798" city="Houston" region="Texas" country="United States" postal="None" date="13/Mar/2012:20:50:18 +0000" request="GET / HTTP/1.1" referer="&quot;http://www.kickstarter.com/projects/1650920829/nimbus&quot;" useragent="Mozilla/4.0 (compatible; MSIE 8.0; Windows NT 6.0; Trident/4.0; GIL 3; SLCC1; .NET CLR 2.0.50727; .NET CLR 1.1.4322; InfoPath.2; .NET CLR 3.5.30729; .NET CLR 3.0.30729; .NET4.0C; .NET4.0E; GIL3)"/>
<marker lat="33.8403015137" lng="-118.353897095" city="Torrance" region="California" country="United States" postal="90503" date="13/Mar/2012:21:07:45 +0000" request="GET / HTTP/1.0" referer="&quot;-&quot;" useragent="Mozilla/Nutch-1.2 (Windows; U; Windows NT 5.1; en-US; rv:1.9.1.11)"/>
<marker lat="53.0" lng="-8.0" city="None" region="None" country="Ireland" postal="None" date="13/Mar/2012:21:17:36 +0000" request="HEAD / HTTP/1.0" referer="&quot;-&quot;" useragent="-"/>
<marker lat="47.0" lng="8.0" city="None" region="None" country="Switzerland" postal="None" date="13/Mar/2012:22:23:27 +0000" request="GET / HTTP/1.1" referer="&quot;http://www.kickstarter.com/projects/1650920829/nimbus?ref=category&quot;" useragent="Mozilla/5.0 (X11; Linux x86_64) AppleWebKit/535.11 (KHTML, like Gecko) Chrome/17.0.963.79 Safari/535.11"/>
<marker lat="23.1166992188" lng="113.25" city="Guangzhou" region="Guangdong" country="China" postal="None" date="13/Mar/2012:22:25:56 +0000" request="GET / HTTP/1.0" referer="&quot;-&quot;" useragent="Mozilla/4.0 (compatible; MSIE 6.0; Windows NT 5.1; SV1; .NET CLR 1.1.4322;TencentTraveler)"/>
<marker lat="31.0049991608" lng="121.408599854" city="Shanghai" region="Shanghai" country="China" postal="None" date="13/Mar/2012:22:36:51 +0000" request="GET / HTTP/1.0" referer="&quot;-&quot;" useragent="Mozilla/4.0 (compatible; MSIE 6.0; Windows NT 5.1; SV1; .NET CLR 1.1.4322;TencentTraveler)"/>
<marker lat="31.0049991608" lng="121.408599854" city="Shanghai" region="Shanghai" country="China" postal="None" date="13/Mar/2012:23:29:31 +0000" request="GET / HTTP/1.0" referer="&quot;-&quot;" useragent="Mozilla/4.0 (compatible; MSIE 6.0; Windows NT 5.1; SV1; .NET CLR 1.1.4322;TencentTraveler)"/>
<marker lat="23.1166992188" lng="113.25" city="Guangzhou" region="Guangdong" country="China" postal="None" date="13/Mar/2012:23:33:43 +0000" request="GET / HTTP/1.0" referer="&quot;-&quot;" useragent="Mozilla/4.0 (compatible; MSIE 6.0; Windows NT 5.1; SV1; .NET CLR 1.1.4322;TencentTraveler)"/>
<marker lat="38.0" lng="-97.0" city="None" region="None" country="United States" postal="None" date="14/Mar/2012:00:24:19 +0000" request="GET / HTTP/1.1" referer="&quot;-&quot;" useragent="Mozilla/5.0 (Windows; U; Windows NT 6.1; en-US; rv:1.9.2.9) Gecko/20100824 Firefox/3.6.9"/>
<marker lat="39.9289016724" lng="116.388298035" city="Beijing" region="Beijing" country="China" postal="None" date="14/Mar/2012:01:29:55 +0000" request="GET / HTTP/1.1" referer="&quot;http://www.hangzhoutongzhi.com/&quot;" useragent="Mozilla/4.0 (compatible; MSIE 6.0; Windows NT 5.1)"/>
<marker lat="1.36670005322" lng="103.800003052" city="None" region="None" country="Singapore" postal="None" date="14/Mar/2012:03:12:47 +0000" request="GET / HTTP/1.1" referer="&quot;http://www.kickstarter.com/projects/1650920829/nimbus&quot;" useragent="Mozilla/5.0 (Windows NT 5.1) AppleWebKit/535.11 (KHTML, like Gecko) Chrome/17.0.963.79 Safari/535.11"/>
<marker lat="40.792098999" lng="-74.1626968384" city="Belleville" region="New Jersey" country="United States" postal="07109" date="14/Mar/2012:03:54:36 +0000" request="GET /resume.html HTTP/1.1" referer="&quot;http://search.yahoo.com/search?n=100&amp;ei=UTF-8&amp;va_vt=any&amp;vo_vt=any&amp;ve_vt=any&amp;vp_vt=any&amp;vd=m3&amp;vst=0&amp;vf=all&amp;vc=us&amp;vm=r&amp;fl=1&amp;vl=lang_en&amp;fr=ush-&amp;p=%22resume.html%22+%22Intel+Corporation%22+-sample+-example+-template+-job+-SUBMIT+-Applicant+java&amp;vs=&quot;" useragent="Mozilla/4.0 (compatible; MSIE 8.0; Windows NT 6.1; SV1; .NET CLR 2.0.50727)"/>
<marker lat="48.8666992188" lng="2.33330011368" city="Paris" region="Ile-de-France" country="France" postal="None" date="14/Mar/2012:05:04:54 +0000" request="GET / HTTP/1.1" referer="&quot;http://www.kickstarter.com/projects/1650920829/nimbus&quot;" useragent="Mozilla/5.0 (Windows NT 6.1; WOW64) AppleWebKit/535.11 (KHTML, like Gecko) Chrome/17.0.963.79 Safari/535.11"/>
<marker lat="31.0049991608" lng="121.408599854" city="Shanghai" region="Shanghai" country="China" postal="None" date="14/Mar/2012:07:51:06 +0000" request="GET / HTTP/1.0" referer="&quot;-&quot;" useragent="Mozilla/4.0 (compatible; MSIE 6.0; Windows NT 5.1; SV1; .NET CLR 1.1.4322;TencentTraveler)"/>
<marker lat="28.6667003632" lng="77.2166976929" city="Delhi" region="Delhi" country="India" postal="None" date="14/Mar/2012:08:34:02 +0000" request="GET / HTTP/1.1" referer="&quot;-&quot;" useragent="-"/>
<marker lat="28.6667003632" lng="77.2166976929" city="Delhi" region="Delhi" country="India" postal="None" date="14/Mar/2012:08:34:03 +0000" request="GET / HTTP/1.1" referer="&quot;-&quot;" useragent="-"/>
<marker lat="23.1166992188" lng="113.25" city="Guangzhou" region="Guangdong" country="China" postal="None" date="14/Mar/2012:08:44:50 +0000" request="GET / HTTP/1.0" referer="&quot;-&quot;" useragent="Mozilla/4.0 (compatible; MSIE 6.0; Windows NT 5.1; SV1; .NET CLR 1.1.4322;TencentTraveler)"/>
<marker lat="35.0" lng="105.0" city="None" region="None" country="China" postal="None" date="14/Mar/2012:09:02:40 +0000" request="HEAD / HTTP/1.0" referer="&quot;-&quot;" useragent="-"/>
<marker lat="23.1166992188" lng="113.25" city="Guangzhou" region="Guangdong" country="China" postal="None" date="14/Mar/2012:09:57:01 +0000" request="GET / HTTP/1.0" referer="&quot;-&quot;" useragent="Mozilla/4.0 (compatible; MSIE 6.0; Windows NT 5.1; SV1; .NET CLR 1.1.4322;TencentTraveler)"/>
<marker lat="58.4166984558" lng="15.6167001724" city="Linkping" region="Ostergotlands Lan" country="Sweden" postal="None" date="14/Mar/2012:10:12:16 +0000" request="GET / HTTP/1.1" referer="&quot;http://www.kickstarter.com/projects/1650920829/nimbus&quot;" useragent="Mozilla/5.0 (Macintosh; Intel Mac OS X 10_7_3) AppleWebKit/534.53.11 (KHTML, like Gecko) Version/5.1.3 Safari/534.53.10"/>
<marker lat="31.0049991608" lng="121.408599854" city="Shanghai" region="Shanghai" country="China" postal="None" date="14/Mar/2012:11:05:15 +0000" request="GET / HTTP/1.0" referer="&quot;-&quot;" useragent="Mozilla/4.0 (compatible; MSIE 6.0; Windows NT 5.1; SV1; .NET CLR 1.1.4322;TencentTraveler)"/>
<marker lat="35.0" lng="105.0" city="None" region="None" country="China" postal="None" date="14/Mar/2012:12:17:40 +0000" request="GET / HTTP/1.1" referer="&quot;-&quot;" useragent="Yahoo! Slurp China"/>
<marker lat="41.0415000916" lng="-85.1502990723" city="Fort Wayne" region="Indiana" country="United States" postal="46807" date="14/Mar/2012:12:56:15 +0000" request="GET / HTTP/1.1" referer="&quot;http://www.kickstarter.com/projects/1650920829/nimbus&quot;" useragent="Mozilla/5.0 (Macintosh; Intel Mac OS X 10_7_3) AppleWebKit/535.11 (KHTML, like Gecko) Chrome/17.0.963.79 Safari/535.11"/>
<marker lat="37.5663986206" lng="126.999702454" city="Seoul" region="Seoul-t'ukpyolsi" country="Korea, Republic of" postal="None" date="14/Mar/2012:13:48:54 +0000" request="GET / HTTP/1.1" referer="&quot;http://www.kickstarter.com/projects/1650920829/nimbus&quot;" useragent="Mozilla/5.0 (Macintosh; Intel Mac OS X 10_7_3) AppleWebKit/534.53.11 (KHTML, like Gecko) Version/5.1.3 Safari/534.53.10"/>
<marker lat="47.6026992798" lng="-122.155601501" city="Bellevue" region="Washington" country="United States" postal="None" date="14/Mar/2012:14:18:39 +0000" request="GET / HTTP/1.1" referer="&quot;-&quot;" useragent="Mozilla/4.0 (compatible; MSIE 7.0; Windows NT 5.1; SLCC1; .NET CLR 1.1.4325; .NET CLR 2.0.40607; .NET CLR 3.0.04506.648)"/>
<marker lat="38.0" lng="-97.0" city="None" region="None" country="United States" postal="None" date="14/Mar/2012:14:19:26 +0000" request="GET / HTTP/1.0" referer="&quot;-&quot;" useragent="Mozilla/5.0 (X11; U; Linux i686; en-US; rv:1.7.5) Gecko/20041107 Firefox/1.0"/>
<marker lat="38.0" lng="-97.0" city="None" region="None" country="United States" postal="None" date="14/Mar/2012:16:37:59 +0000" request="GET /resume.html HTTP/1.1" referer="&quot;http://search.yahoo.com/search?n=100&amp;ei=UTF-8&amp;va_vt=any&amp;vo_vt=any&amp;ve_vt=any&amp;vp_vt=any&amp;vd=m3&amp;vst=0&amp;vf=all&amp;vc=us&amp;vm=r&amp;fl=1&amp;vl=lang_en&amp;fr=ush-&amp;p=%22resume.html%22+%22Intel+Corporation%22+-sample+-example+-template+-job+-SUBMIT+-Applicant++ios&amp;vs=&quot;" useragent="Mozilla/4.0 (compatible; MSIE 8.0; Windows NT 6.1; SV1; .NET CLR 2.0.50727)"/>
<marker lat="41.1500015259" lng="-8.61670017242" city="Porto" region="Porto" country="Portugal" postal="None" date="14/Mar/2012:17:17:18 +0000" request="GET / HTTP/1.0" referer="&quot;http://www.kickstarter.com/projects/1650920829/nimbus?ref=category&quot;" useragent="Mozilla/5.0 (Windows NT 6.1) AppleWebKit/535.19 (KHTML, like Gecko) Chrome/18.0.1025.56 Safari/535.19"/>
<marker lat="45.5183982849" lng="-122.655403137" city="Portland" region="Oregon" country="United States" postal="None" date="14/Mar/2012:17:34:23 +0000" request="GET / HTTP/1.1" referer="&quot;http://www.kickstarter.com/projects/1650920829/nimbus&quot;" useragent="Mozilla/5.0 (Macintosh; Intel Mac OS X 10_7_3) AppleWebKit/535.11 (KHTML, like Gecko) Chrome/17.0.963.79 Safari/535.11"/>
<marker lat="51.0" lng="9.0" city="None" region="None" country="Germany" postal="None" date="14/Mar/2012:17:37:35 +0000" request="GET / HTTP/1.1" referer="&quot;-&quot;" useragent="Mozilla/5.0 (compatible; SISTRIX Crawler; http://crawler.sistrix.net/)"/>
<marker lat="51.0" lng="9.0" city="None" region="None" country="Germany" postal="None" date="14/Mar/2012:17:37:36 +0000" request="GET /index.html HTTP/1.1" referer="&quot;-&quot;" useragent="Mozilla/5.0 (compatible; SISTRIX Crawler; http://crawler.sistrix.net/)"/>
<marker lat="51.0" lng="9.0" city="None" region="None" country="Germany" postal="None" date="14/Mar/2012:17:37:36 +0000" request="GET /resume.html HTTP/1.1" referer="&quot;-&quot;" useragent="Mozilla/5.0 (compatible; SISTRIX Crawler; http://crawler.sistrix.net/)"/>
<marker lat="44.8833007812" lng="-0.40000000596" city="Beychac-et-caillau" region="Aquitaine" country="France" postal="None" date="14/Mar/2012:17:40:41 +0000" request="GET / HTTP/1.1" referer="&quot;http://www.kickstarter.com/projects/1650920829/nimbus?ref=card&quot;" useragent="Mozilla/5.0 (X11; Ubuntu; Linux x86_64; rv:11.0) Gecko/20100101 Firefox/11.0"/>
<marker lat="28.6667003632" lng="77.2166976929" city="Delhi" region="Delhi" country="India" postal="None" date="14/Mar/2012:18:27:12 +0000" request="GET / HTTP/1.1" referer="&quot;http://www.kickstarter.com/projects/1650920829/nimbus&quot;" useragent="Mozilla/5.0 (Windows NT 6.1) AppleWebKit/535.11 (KHTML, like Gecko) Chrome/17.0.963.78 Safari/535.11"/>
<marker lat="42.6488990784" lng="-71.1654968262" city="Andover" region="Massachusetts" country="United States" postal="01810" date="14/Mar/2012:18:31:06 +0000" request="GET / HTTP/1.1" referer="&quot;http://www.kickstarter.com/projects/1650920829/nimbus&quot;" useragent="Mozilla/5.0 (Windows NT 6.1; WOW64) AppleWebKit/535.11 (KHTML, like Gecko) Chrome/17.0.963.56 Safari/535.11"/>
<marker lat="34.4328994751" lng="-119.837097168" city="Santa Barbara" region="California" country="United States" postal="93106" date="14/Mar/2012:18:43:46 +0000" request="GET / HTTP/1.1" referer="&quot;-&quot;" useragent="Mozilla/5.0 (X11; Linux x86_64) AppleWebKit/535.11 (KHTML, like Gecko) Chrome/17.0.963.79 Safari/535.11"/>
<marker lat="55.1666984558" lng="-118.800003052" city="Grande Prairie" region="Alberta" country="Canada" postal="None" date="14/Mar/2012:18:51:23 +0000" request="GET / HTTP/1.1" referer="&quot;http://www.kickstarter.com/projects/1650920829/nimbus?ref=category&quot;" useragent="Mozilla/4.0 (compatible; MSIE 8.0; Windows NT 6.1; WOW64; Trident/4.0; SLCC2; .NET CLR 2.0.50727; .NET CLR 3.5.30729; .NET CLR 3.0.30729; .NET4.0C; .NET4.0E)"/>
<marker lat="36.4062995911" lng="-119.380897522" city="Visalia" region="California" country="United States" postal="93291" date="14/Mar/2012:19:44:31 +0000" request="GET / HTTP/1.1" referer="&quot;-&quot;" useragent="Mozilla/5.0 (Macintosh; Intel Mac OS X 10_7_3) AppleWebKit/535.19 (KHTML, like Gecko) Chrome/18.0.1025.54 Safari/535.19"/>
<marker lat="38.0" lng="-97.0" city="None" region="None" country="United States" postal="None" date="14/Mar/2012:20:43:21 +0000" request="GET /resume.html HTTP/1.1" referer="&quot;http://search.yahoo.com/search?n=100&amp;ei=UTF-8&amp;va_vt=any&amp;vo_vt=any&amp;ve_vt=any&amp;vp_vt=any&amp;vd=y&amp;vst=0&amp;vf=all&amp;vc=us&amp;vm=r&amp;fl=1&amp;vl=lang_en&amp;fr=ush-&amp;p=%22resume.html%22+%22Intel+Corporation%22+-sample+-example+-template+-job+-SUBMIT+-Applicant++and+-xerox+-ADP+-POS+-%22Point+of+Sale%22+-%22payroll+systems%22&amp;vs=&quot;" useragent="Mozilla/4.0 (compatible; MSIE 8.0; Windows NT 6.1; SV1; .NET CLR 2.0.50727)"/>
<marker lat="23.1166992188" lng="113.25" city="Guangzhou" region="Guangdong" country="China" postal="None" date="14/Mar/2012:23:14:17 +0000" request="GET / HTTP/1.0" referer="&quot;-&quot;" useragent="Mozilla/4.0 (compatible; MSIE 6.0; Windows NT 5.1; SV1; .NET CLR 1.1.4322;TencentTraveler)"/>
<marker lat="54.5358009338" lng="36.2705993652" city="Kaluga" region="Kaluga" country="Russian Federation" postal="None" date="14/Mar/2012:23:37:36 +0000" request="GET / HTTP/1.1" referer="&quot;-&quot;" useragent="Mozilla/5.0 (Macintosh; Intel Mac OS X 10_7_3) AppleWebKit/534.54.16 (KHTML, like Gecko) Version/5.1.4 Safari/534.54.16"/>
<marker lat="23.1166992188" lng="113.25" city="Guangzhou" region="Guangdong" country="China" postal="None" date="14/Mar/2012:23:39:58 +0000" request="GET / HTTP/1.0" referer="&quot;-&quot;" useragent="Mozilla/4.0 (compatible; MSIE 6.0; Windows NT 5.1; SV1; .NET CLR 1.1.4322;TencentTraveler)"/>
<marker lat="31.0049991608" lng="121.408599854" city="Shanghai" region="Shanghai" country="China" postal="None" date="14/Mar/2012:23:43:43 +0000" request="GET / HTTP/1.0" referer="&quot;-&quot;" useragent="Mozilla/4.0 (compatible; MSIE 6.0; Windows NT 5.1; SV1; .NET CLR 1.1.4322;TencentTraveler)"/>
<marker lat="31.0049991608" lng="121.408599854" city="Shanghai" region="Shanghai" country="China" postal="None" date="14/Mar/2012:23:50:11 +0000" request="GET / HTTP/1.0" referer="&quot;-&quot;" useragent="Mozilla/4.0 (compatible; MSIE 6.0; Windows NT 5.1; SV1; .NET CLR 1.1.4322;TencentTraveler)"/>
<marker lat="25.0391998291" lng="121.525001526" city="Taipei" region="T'ai-pei" country="Taiwan" postal="None" date="15/Mar/2012:00:05:02 +0000" request="GET HTTP/1.1&quot; 40" referer="&quot;-&quot;" useragent=""/>
<marker lat="39.9289016724" lng="116.388298035" city="Beijing" region="Beijing" country="China" postal="None" date="15/Mar/2012:01:33:41 +0000" request="GET / HTTP/1.1" referer="&quot;http://www.hangzhoutongzhi.com/&quot;" useragent="Mozilla/4.0 (compatible; MSIE 6.0; Windows NT 5.1)"/>
<marker lat="40.792098999" lng="-74.1626968384" city="Belleville" region="New Jersey" country="United States" postal="07109" date="15/Mar/2012:03:54:04 +0000" request="GET /resume.html HTTP/1.1" referer="&quot;http://search.yahoo.com/search?n=100&amp;ei=UTF-8&amp;va_vt=any&amp;vo_vt=any&amp;ve_vt=any&amp;vp_vt=any&amp;vd=m3&amp;vst=0&amp;vf=all&amp;vc=us&amp;vm=r&amp;fl=1&amp;vl=lang_en&amp;fr=ush-&amp;p=%22resume.html%22+%22Intel+Corporation%22+-sample+-example+-template+-job+-SUBMIT+-Applicant+java&amp;vs=&quot;" useragent="Mozilla/4.0 (compatible; MSIE 8.0; Windows NT 6.1; SV1; .NET CLR 2.0.50727)"/>
<marker lat="23.1166992188" lng="113.25" city="Guangzhou" region="Guangdong" country="China" postal="None" date="15/Mar/2012:05:40:16 +0000" request="GET / HTTP/1.0" referer="&quot;-&quot;" useragent="Mozilla/4.0 (compatible; MSIE 6.0; Windows NT 5.1; SV1; .NET CLR 1.1.4322;TencentTraveler)"/>
<marker lat="31.0049991608" lng="121.408599854" city="Shanghai" region="Shanghai" country="China" postal="None" date="15/Mar/2012:06:07:48 +0000" request="GET / HTTP/1.0" referer="&quot;-&quot;" useragent="Mozilla/4.0 (compatible; MSIE 6.0; Windows NT 5.1; SV1; .NET CLR 1.1.4322;TencentTraveler)"/>
<marker lat="23.1166992188" lng="113.25" city="Guangzhou" region="Guangdong" country="China" postal="None" date="15/Mar/2012:07:28:47 +0000" request="GET / HTTP/1.0" referer="&quot;-&quot;" useragent="Mozilla/4.0 (compatible; MSIE 6.0; Windows NT 5.1; SV1; .NET CLR 1.1.4322;TencentTraveler)"/>
<marker lat="38.0" lng="-97.0" city="None" region="None" country="United States" postal="None" date="15/Mar/2012:07:42:22 +0000" request="GET /resume.html HTTP/1.1" referer="&quot;http://search.yahoo.com/search?n=100&amp;ei=UTF-8&amp;va_vt=any&amp;vo_vt=any&amp;ve_vt=any&amp;vp_vt=any&amp;vd=m3&amp;vst=0&amp;vf=all&amp;vc=us&amp;vm=r&amp;fl=1&amp;vl=lang_en&amp;fr=ush-&amp;p=%22resume.html%22+%22Intel+Corporation%22+-sample+-example+-template+-job+-SUBMIT+-Applicant++java+JavaScript&amp;vs=&quot;" useragent="Mozilla/4.0 (compatible; MSIE 8.0; Windows NT 6.1; SV1; .NET CLR 2.0.50727)"/>
<marker lat="31.0049991608" lng="121.408599854" city="Shanghai" region="Shanghai" country="China" postal="None" date="15/Mar/2012:08:21:29 +0000" request="GET / HTTP/1.1" referer="&quot;-&quot;" useragent="Mozilla/5.0 (Windows NT 6.1) AppleWebKit/536.3 (KHTML, like Gecko) Chrome/19.0.1061.1 Safari/536.3"/>
<marker lat="31.0049991608" lng="121.408599854" city="Shanghai" region="Shanghai" country="China" postal="None" date="15/Mar/2012:08:21:31 +0000" request="GET /stylesheets/base.css HTTP/1.1" referer="&quot;http://semjy.com/&quot;" useragent="Mozilla/5.0 (Windows NT 6.1) AppleWebKit/536.3 (KHTML, like Gecko) Chrome/19.0.1061.1 Safari/536.3"/>
<marker lat="31.0049991608" lng="121.408599854" city="Shanghai" region="Shanghai" country="China" postal="None" date="15/Mar/2012:08:21:31 +0000" request="GET /stylesheets/skeleton.css HTTP/1.1" referer="&quot;http://semjy.com/&quot;" useragent="Mozilla/5.0 (Windows NT 6.1) AppleWebKit/536.3 (KHTML, like Gecko) Chrome/19.0.1061.1 Safari/536.3"/>
<marker lat="31.0049991608" lng="121.408599854" city="Shanghai" region="Shanghai" country="China" postal="None" date="15/Mar/2012:08:21:32 +0000" request="GET /stylesheets/layout.css HTTP/1.1" referer="&quot;http://semjy.com/&quot;" useragent="Mozilla/5.0 (Windows NT 6.1) AppleWebKit/536.3 (KHTML, like Gecko) Chrome/19.0.1061.1 Safari/536.3"/>
<marker lat="31.0049991608" lng="121.408599854" city="Shanghai" region="Shanghai" country="China" postal="None" date="15/Mar/2012:08:21:32 +0000" request="GET /javascripts/tabs.js HTTP/1.1" referer="&quot;http://semjy.com/&quot;" useragent="Mozilla/5.0 (Windows NT 6.1) AppleWebKit/536.3 (KHTML, like Gecko) Chrome/19.0.1061.1 Safari/536.3"/>
<marker lat="31.0049991608" lng="121.408599854" city="Shanghai" region="Shanghai" country="China" postal="None" date="15/Mar/2012:08:21:32 +0000" request="GET /stylesheets/custom.css HTTP/1.1" referer="&quot;http://semjy.com/&quot;" useragent="Mozilla/5.0 (Windows NT 6.1) AppleWebKit/536.3 (KHTML, like Gecko) Chrome/19.0.1061.1 Safari/536.3"/>
<marker lat="31.0049991608" lng="121.408599854" city="Shanghai" region="Shanghai" country="China" postal="None" date="15/Mar/2012:08:21:32 +0000" request="GET /images/me.png HTTP/1.1" referer="&quot;http://semjy.com/&quot;" useragent="Mozilla/5.0 (Windows NT 6.1) AppleWebKit/536.3 (KHTML, like Gecko) Chrome/19.0.1061.1 Safari/536.3"/>
<marker lat="36.3596992493" lng="-119.315498352" city="Visalia" region="California" country="United States" postal="None" date="15/Mar/2012:08:35:14 +0000" request="GET / HTTP/1.1" referer="&quot;-&quot;" useragent="Mozilla/5.0 (Macintosh; Intel Mac OS X 10_7_3) AppleWebKit/535.19 (KHTML, like Gecko) Chrome/18.0.1025.54 Safari/535.19"/>
<marker lat="36.3596992493" lng="-119.315498352" city="Visalia" region="California" country="United States" postal="None" date="15/Mar/2012:08:37:01 +0000" request="GET / HTTP/1.1" referer="&quot;-&quot;" useragent="Mozilla/5.0 (Macintosh; Intel Mac OS X 10_7_3) AppleWebKit/535.19 (KHTML, like Gecko) Chrome/18.0.1025.54 Safari/535.19"/>
<marker lat="36.3596992493" lng="-119.315498352" city="Visalia" region="California" country="United States" postal="None" date="15/Mar/2012:08:45:51 +0000" request="GET / HTTP/1.1" referer="&quot;-&quot;" useragent="Mozilla/5.0 (Macintosh; Intel Mac OS X 10_7_3) AppleWebKit/535.19 (KHTML, like Gecko) Chrome/18.0.1025.54 Safari/535.19"/>
<marker lat="39.9289016724" lng="116.388298035" city="Beijing" region="Beijing" country="China" postal="None" date="15/Mar/2012:08:55:39 +0000" request="GET / HTTP/1.1" referer="&quot;http://www.hangzhoutongzhi.com/&quot;" useragent="Mozilla/4.0 (compatible; MSIE 6.0; Windows NT 5.1)"/>
<marker lat="31.0049991608" lng="121.408599854" city="Shanghai" region="Shanghai" country="China" postal="None" date="15/Mar/2012:08:56:41 +0000" request="GET / HTTP/1.0" referer="&quot;-&quot;" useragent="Mozilla/4.0 (compatible; MSIE 6.0; Windows NT 5.1; SV1; .NET CLR 1.1.4322;TencentTraveler)"/>
<marker lat="36.3596992493" lng="-119.315498352" city="Visalia" region="California" country="United States" postal="None" date="15/Mar/2012:09:12:05 +0000" request="GET / HTTP/1.1" referer="&quot;-&quot;" useragent="Mozilla/5.0 (Macintosh; Intel Mac OS X 10_7_3) AppleWebKit/535.19 (KHTML, like Gecko) Chrome/18.0.1025.54 Safari/535.19"/>
<marker lat="35.0" lng="105.0" city="None" region="None" country="China" postal="None" date="15/Mar/2012:09:36:52 +0000" request="HEAD / HTTP/1.0" referer="&quot;-&quot;" useragent="-"/>
<marker lat="20.0" lng="77.0" city="None" region="None" country="India" postal="None" date="15/Mar/2012:10:34:50 +0000" request="GET / HTTP/1.1" referer="&quot;http://www.kickstarter.com/projects/1650920829/nimbus?ref=category&quot;" useragent="Mozilla/5.0 (Windows NT 5.1; rv:10.0.2) Gecko/20100101 Firefox/10.0.2"/>
<marker lat="45.4832992554" lng="9.28330039978" city="Segrate" region="Lombardia" country="Italy" postal="None" date="15/Mar/2012:11:05:53 +0000" request="GET / HTTP/1.1" referer="&quot;http://www.kickstarter.com/projects/1650920829/nimbus&quot;" useragent="Mozilla/5.0 (Macintosh; Intel Mac OS X 10.7; rv:11.0) Gecko/20100101 Firefox/11.0"/>
<marker lat="40.4000015259" lng="-3.68330001831" city="Madrid" region="Madrid" country="Spain" postal="None" date="15/Mar/2012:12:07:36 +0000" request="GET / HTTP/1.0" referer="&quot;http://www.kickstarter.com/projects/1650920829/nimbus&quot;" useragent="Mozilla/5.0 (Macintosh; Intel Mac OS X 10.7; rv:10.0.2) Gecko/20100101 Firefox/10.0.2"/>
<marker lat="48.6666984558" lng="19.5" city="None" region="None" country="Slovakia" postal="None" date="15/Mar/2012:12:48:38 +0000" request="GET / HTTP/1.1" referer="&quot;http://www.kickstarter.com/projects/1650920829/nimbus?ref=card&quot;" useragent="Mozilla/5.0 (Windows NT 6.1) AppleWebKit/535.11 (KHTML, like Gecko) Chrome/17.0.963.79 Safari/535.11"/>
<marker lat="52.4166984558" lng="-1.54999995232" city="Coventry" region="Coventry" country="United Kingdom" postal="None" date="15/Mar/2012:14:40:36 +0000" request="GET / HTTP/1.1" referer="&quot;http://www.kickstarter.com/projects/1650920829/nimbus&quot;" useragent="Mozilla/5.0 (Macintosh; Intel Mac OS X 10_7_3) AppleWebKit/535.11 (KHTML, like Gecko) Chrome/17.0.963.79 Safari/535.11"/>
<marker lat="38.0" lng="-97.0" city="None" region="None" country="United States" postal="None" date="15/Mar/2012:15:01:12 +0000" request="GET /resume.html HTTP/1.1" referer="&quot;http://search.yahoo.com/search?n=100&amp;ei=UTF-8&amp;va_vt=any&amp;vo_vt=any&amp;ve_vt=any&amp;vp_vt=any&amp;vd=m3&amp;vst=0&amp;vf=all&amp;vc=us&amp;vm=r&amp;fl=1&amp;vl=lang_en&amp;fr=ush-&amp;p=%22resume.html%22+%22Intel+Corporation%22+-sample+-example+-template+-job+-SUBMIT+-Applicant+&amp;vs=&quot;" useragent="Mozilla/4.0 (compatible; MSIE 8.0; Windows NT 6.1; SV1; .NET CLR 2.0.50727)"/>
<marker lat="42.8333015442" lng="12.8332996368" city="None" region="None" country="Italy" postal="None" date="15/Mar/2012:16:18:13 +0000" request="GET / HTTP/1.1" referer="&quot;http://www.kickstarter.com/projects/1650920829/nimbus?ref=card&quot;" useragent="Mozilla/5.0 (Windows NT 5.1; rv:11.0) Gecko/20100101 Firefox/11.0"/>
<marker lat="38.0" lng="-97.0" city="None" region="None" country="United States" postal="None" date="15/Mar/2012:16:53:52 +0000" request="GET /resume.html HTTP/1.1" referer="&quot;http://search.yahoo.com/search?n=100&amp;ei=UTF-8&amp;va_vt=any&amp;vo_vt=any&amp;ve_vt=any&amp;vp_vt=any&amp;vd=y&amp;vst=0&amp;vf=all&amp;vc=us&amp;vm=r&amp;fl=1&amp;vl=lang_en&amp;fr=ush-&amp;p=%22resume.html%22+%22Intel+Corporation%22+-sample+-example+-template+-job+-SUBMIT+-Applicant++Data+development+-recruiter&amp;vs=&quot;" useragent="Mozilla/4.0 (compatible; MSIE 8.0; Windows NT 6.1; SV1; .NET CLR 2.0.50727)"/>
<marker lat="41.4286003113" lng="-73.1424026489" city="Oxford" region="Connecticut" country="United States" postal="06478" date="15/Mar/2012:17:08:03 +0000" request="GET / HTTP/1.1" referer="&quot;http://www.kickstarter.com/projects/1650920829/nimbus&quot;" useragent="Mozilla/5.0 (Windows NT 6.1; rv:10.0.2) Gecko/20100101 Firefox/10.0.2"/>
<marker lat="38.0" lng="-97.0" city="None" region="None" country="United States" postal="None" date="15/Mar/2012:17:08:04 +0000" request="GET / HTTP/1.1" referer="&quot;-&quot;" useragent="Mozilla/5.0 (Windows NT 6.1; rv:10.0.2) Gecko/20100101 Firefox/10.0.2"/>
<marker lat="32.8568992615" lng="-96.9628982544" city="Irving" region="Texas" country="United States" postal="None" date="15/Mar/2012:17:12:59 +0000" request="GET / HTTP/1.1" referer="&quot;http://www.kickstarter.com/projects/1650920829/nimbus&quot;" useragent="Mozilla/5.0 (Macintosh; Intel Mac OS X 10_7_3) AppleWebKit/535.11 (KHTML, like Gecko) Chrome/17.0.963.79 Safari/535.11"/>
<marker lat="50.1166992188" lng="8.68330001831" city="Frankfurt Am Main" region="Hessen" country="Germany" postal="None" date="15/Mar/2012:17:59:32 +0000" request="GET / HTTP/1.1" referer="&quot;http://www.kickstarter.com/projects/1650920829/nimbus?ref=card&quot;" useragent="Mozilla/5.0 (Windows NT 6.0; WOW64) AppleWebKit/535.19 (KHTML, like Gecko) Chrome/18.0.1025.58 Safari/535.19"/>
<marker lat="38.0" lng="-97.0" city="None" region="None" country="United States" postal="None" date="15/Mar/2012:21:07:14 +0000" request="GET /resume.html HTTP/1.1" referer="&quot;http://search.yahoo.com/search?n=100&amp;ei=UTF-8&amp;va_vt=any&amp;vo_vt=any&amp;ve_vt=any&amp;vp_vt=any&amp;vd=m3&amp;vst=0&amp;vf=all&amp;vc=us&amp;vm=r&amp;fl=1&amp;vl=lang_en&amp;fr=ush-&amp;p=%22resume.html%22+%22Intel+Corporation%22+-sample+-example+-template+-job+-SUBMIT+-Applicant+&amp;vs=&quot;" useragent="Mozilla/4.0 (compatible; MSIE 8.0; Windows NT 6.1; SV1; .NET CLR 2.0.50727)"/>
<marker lat="34.0535011292" lng="-84.06590271" city="Suwanee" region="Georgia" country="United States" postal="30024" date="15/Mar/2012:21:37:22 +0000" request="GET / HTTP/1.1" referer="&quot;-&quot;" useragent="Mozilla/5.0 (Windows NT 6.1; WOW64; rv:11.0) Gecko/20100101 Firefox/11.0"/>
<marker lat="34.0535011292" lng="-84.06590271" city="Suwanee" region="Georgia" country="United States" postal="30024" date="15/Mar/2012:21:37:22 +0000" request="GET /stylesheets/base.css HTTP/1.1" referer="&quot;-&quot;" useragent="Mozilla/5.0 (Windows NT 6.1; WOW64; rv:11.0) Gecko/20100101 Firefox/11.0"/>
<marker lat="34.0535011292" lng="-84.06590271" city="Suwanee" region="Georgia" country="United States" postal="30024" date="15/Mar/2012:21:37:22 +0000" request="GET /stylesheets/skeleton.css HTTP/1.1" referer="&quot;-&quot;" useragent="Mozilla/5.0 (Windows NT 6.1; WOW64; rv:11.0) Gecko/20100101 Firefox/11.0"/>
<marker lat="34.0535011292" lng="-84.06590271" city="Suwanee" region="Georgia" country="United States" postal="30024" date="15/Mar/2012:21:37:22 +0000" request="GET /javascripts/tabs.js HTTP/1.1" referer="&quot;-&quot;" useragent="Mozilla/5.0 (Windows NT 6.1; WOW64; rv:11.0) Gecko/20100101 Firefox/11.0"/>
<marker lat="34.0535011292" lng="-84.06590271" city="Suwanee" region="Georgia" country="United States" postal="30024" date="15/Mar/2012:21:37:22 +0000" request="GET /stylesheets/layout.css HTTP/1.1" referer="&quot;-&quot;" useragent="Mozilla/5.0 (Windows NT 6.1; WOW64; rv:11.0) Gecko/20100101 Firefox/11.0"/>
<marker lat="34.0535011292" lng="-84.06590271" city="Suwanee" region="Georgia" country="United States" postal="30024" date="15/Mar/2012:21:37:22 +0000" request="GET /stylesheets/custom.css HTTP/1.1" referer="&quot;-&quot;" useragent="Mozilla/5.0 (Windows NT 6.1; WOW64; rv:11.0) Gecko/20100101 Firefox/11.0"/>
<marker lat="34.0535011292" lng="-84.06590271" city="Suwanee" region="Georgia" country="United States" postal="30024" date="15/Mar/2012:21:37:22 +0000" request="GET /images/me.png HTTP/1.1" referer="&quot;-&quot;" useragent="Mozilla/5.0 (Windows NT 6.1; WOW64; rv:11.0) Gecko/20100101 Firefox/11.0"/>
<marker lat="45.4832992554" lng="9.28330039978" city="Segrate" region="Lombardia" country="Italy" postal="None" date="15/Mar/2012:22:38:07 +0000" request="GET / HTTP/1.1" referer="&quot;http://www.kickstarter.com/projects/1650920829/nimbus&quot;" useragent="Mozilla/5.0 (Macintosh; Intel Mac OS X 10_7_3) AppleWebKit/535.11 (KHTML, like Gecko) Chrome/17.0.963.79 Safari/535.11"/>
<marker lat="36.4986991882" lng="-119.279701233" city="Cutler" region="California" country="United States" postal="93615" date="15/Mar/2012:23:04:52 +0000" request="GET / HTTP/1.1" referer="&quot;-&quot;" useragent="Mozilla/5.0 (Macintosh; Intel Mac OS X 10_7_3) AppleWebKit/535.19 (KHTML, like Gecko) Chrome/18.0.1025.54 Safari/535.19"/>
<marker lat="37.4225006104" lng="-122.142303467" city="Palo Alto" region="California" country="United States" postal="None" date="15/Mar/2012:23:12:54 +0000" request="GET / HTTP/1.1" referer="&quot;-&quot;" useragent="Mozilla/5.0 (Macintosh; Intel Mac OS X 10_7_3) AppleWebKit/534.54.16 (KHTML, like Gecko) Version/5.1.4 Safari/534.54.16"/>
<marker lat="36.4986991882" lng="-119.279701233" city="Cutler" region="California" country="United States" postal="93615" date="15/Mar/2012:23:15:23 +0000" request="GET / HTTP/1.1" referer="&quot;-&quot;" useragent="Mozilla/5.0 (Macintosh; Intel Mac OS X 10_7_3) AppleWebKit/535.19 (KHTML, like Gecko) Chrome/18.0.1025.54 Safari/535.19"/>
<marker lat="36.4986991882" lng="-119.279701233" city="Cutler" region="California" country="United States" postal="93615" date="15/Mar/2012:23:15:26 +0000" request="GET / HTTP/1.1" referer="&quot;-&quot;" useragent="Mozilla/5.0 (Macintosh; Intel Mac OS X 10_7_3) AppleWebKit/535.19 (KHTML, like Gecko) Chrome/18.0.1025.54 Safari/535.19"/>
<marker lat="34.0415992737" lng="-118.298797607" city="Los Angeles" region="California" country="United States" postal="None" date="15/Mar/2012:23:16:46 +0000" request="GET / HTTP/1.1" referer="&quot;-&quot;" useragent="Mozilla/5.0 (Macintosh; Intel Mac OS X 10_7_3) AppleWebKit/535.19 (KHTML, like Gecko) Chrome/18.0.1025.54 Safari/535.19"/>
<marker lat="31.0049991608" lng="121.408599854" city="Shanghai" region="Shanghai" country="China" postal="None" date="16/Mar/2012:00:07:25 +0000" request="GET / HTTP/1.0" referer="&quot;-&quot;" useragent="Mozilla/4.0 (compatible; MSIE 6.0; Windows NT 5.1; SV1; .NET CLR 1.1.4322;TencentTraveler)"/>
<marker lat="23.1166992188" lng="113.25" city="Guangzhou" region="Guangdong" country="China" postal="None" date="16/Mar/2012:00:24:13 +0000" request="GET / HTTP/1.0" referer="&quot;-&quot;" useragent="Mozilla/4.0 (compatible; MSIE 6.0; Windows NT 5.1; SV1; .NET CLR 1.1.4322;TencentTraveler)"/>
<marker lat="23.1166992188" lng="113.25" city="Guangzhou" region="Guangdong" country="China" postal="None" date="16/Mar/2012:00:54:22 +0000" request="GET / HTTP/1.0" referer="&quot;-&quot;" useragent="Mozilla/4.0 (compatible; MSIE 6.0; Windows NT 5.1; SV1; .NET CLR 1.1.4322;TencentTraveler)"/>
<marker lat="31.0049991608" lng="121.408599854" city="Shanghai" region="Shanghai" country="China" postal="None" date="16/Mar/2012:01:26:10 +0000" request="GET / HTTP/1.0" referer="&quot;-&quot;" useragent="Mozilla/4.0 (compatible; MSIE 6.0; Windows NT 5.1; SV1; .NET CLR 1.1.4322;TencentTraveler)"/>
<marker lat="40.792098999" lng="-74.1626968384" city="Belleville" region="New Jersey" country="United States" postal="07109" date="16/Mar/2012:03:52:43 +0000" request="GET /resume.html HTTP/1.1" referer="&quot;http://search.yahoo.com/search?n=100&amp;ei=UTF-8&amp;va_vt=any&amp;vo_vt=any&amp;ve_vt=any&amp;vp_vt=any&amp;vd=m3&amp;vst=0&amp;vf=all&amp;vc=us&amp;vm=r&amp;fl=1&amp;vl=lang_en&amp;fr=ush-&amp;p=%22resume.html%22+%22Intel+Corporation%22+-sample+-example+-template+-job+-SUBMIT+-Applicant+java&amp;vs=&quot;" useragent="Mozilla/4.0 (compatible; MSIE 8.0; Windows NT 6.1; SV1; .NET CLR 2.0.50727)"/>
<marker lat="35.0" lng="105.0" city="None" region="None" country="China" postal="None" date="16/Mar/2012:05:26:49 +0000" request="HEAD / HTTP/1.0" referer="&quot;-&quot;" useragent="-"/>
<marker lat="36.4986991882" lng="-119.279701233" city="Cutler" region="California" country="United States" postal="93615" date="16/Mar/2012:05:49:57 +0000" request="GET / HTTP/1.1" referer="&quot;-&quot;" useragent="Mozilla/5.0 (Macintosh; Intel Mac OS X 10_7_3) AppleWebKit/535.19 (KHTML, like Gecko) Chrome/18.0.1025.54 Safari/535.19"/>
<marker lat="22.5697002411" lng="88.3696975708" city="Calcutta" region="West Bengal" country="India" postal="None" date="16/Mar/2012:06:12:32 +0000" request="GET HTTP/1.1 HTTP/1.1" referer="&quot;-&quot;" useragent="Mozilla/5.0 (Windows NT 6.1) AppleWebKit/535.1 (KHTML, like Gecko) Chrome/13.0.782.220 Safari/535.1"/>
<marker lat="22.5697002411" lng="88.3696975708" city="Calcutta" region="West Bengal" country="India" postal="None" date="16/Mar/2012:06:13:21 +0000" request="GET HTTP/1.1&quot; 40" referer="&quot;-&quot;" useragent=""/>
<marker lat="27.8222999573" lng="-82.2797012329" city="Riverview" region="Florida" country="United States" postal="33579" date="16/Mar/2012:06:33:17 +0000" request="GET / HTTP/1.1" referer="&quot;-&quot;" useragent="Mozilla/4.0 (compatible; MSIE 5.5; Windows 98)"/>
<marker lat="23.1166992188" lng="113.25" city="Guangzhou" region="Guangdong" country="China" postal="None" date="16/Mar/2012:07:29:12 +0000" request="GET / HTTP/1.0" referer="&quot;-&quot;" useragent="Mozilla/4.0 (compatible; MSIE 6.0; Windows NT 5.1; SV1; .NET CLR 1.1.4322;TencentTraveler)"/>
<marker lat="31.0049991608" lng="121.408599854" city="Shanghai" region="Shanghai" country="China" postal="None" date="16/Mar/2012:07:53:25 +0000" request="GET / HTTP/1.0" referer="&quot;-&quot;" useragent="Mozilla/4.0 (compatible; MSIE 6.0; Windows NT 5.1; SV1; .NET CLR 1.1.4322;TencentTraveler)"/>
<marker lat="36.4986991882" lng="-119.279701233" city="Cutler" region="California" country="United States" postal="93615" date="16/Mar/2012:08:36:12 +0000" request="GET / HTTP/1.1" referer="&quot;-&quot;" useragent="Mozilla/5.0 (Macintosh; Intel Mac OS X 10_7_3) AppleWebKit/535.19 (KHTML, like Gecko) Chrome/18.0.1025.54 Safari/535.19"/>
<marker lat="36.4986991882" lng="-119.279701233" city="Cutler" region="California" country="United States" postal="93615" date="16/Mar/2012:08:36:29 +0000" request="GET / HTTP/1.1" referer="&quot;-&quot;" useragent="Mozilla/5.0 (Macintosh; Intel Mac OS X 10_7_3) AppleWebKit/535.19 (KHTML, like Gecko) Chrome/18.0.1025.54 Safari/535.19"/>
<marker lat="36.4986991882" lng="-119.279701233" city="Cutler" region="California" country="United States" postal="93615" date="16/Mar/2012:09:27:26 +0000" request="GET / HTTP/1.1" referer="&quot;-&quot;" useragent="Mozilla/5.0 (Macintosh; Intel Mac OS X 10_7_3) AppleWebKit/535.19 (KHTML, like Gecko) Chrome/18.0.1025.100 Safari/535.19"/>
<marker lat="23.1166992188" lng="113.25" city="Guangzhou" region="Guangdong" country="China" postal="None" date="16/Mar/2012:09:52:31 +0000" request="GET / HTTP/1.0" referer="&quot;-&quot;" useragent="Mozilla/4.0 (compatible; MSIE 6.0; Windows NT 5.1; SV1; .NET CLR 1.1.4322;TencentTraveler)"/>
<marker lat="31.0049991608" lng="121.408599854" city="Shanghai" region="Shanghai" country="China" postal="None" date="16/Mar/2012:10:27:49 +0000" request="GET / HTTP/1.0" referer="&quot;-&quot;" useragent="Mozilla/4.0 (compatible; MSIE 6.0; Windows NT 5.1; SV1; .NET CLR 1.1.4322;TencentTraveler)"/>
<marker lat="23.1166992188" lng="113.25" city="Guangzhou" region="Guangdong" country="China" postal="None" date="16/Mar/2012:12:42:30 +0000" request="GET / HTTP/1.1" referer="&quot;-&quot;" useragent="Mozilla/4.0 (compatible; MSIE 6.0; Windows NT 5.1)"/>
<marker lat="23.1166992188" lng="113.25" city="Guangzhou" region="Guangdong" country="China" postal="None" date="16/Mar/2012:12:42:40 +0000" request="GET /stylesheets/custom.css HTTP/1.1" referer="&quot;http://www.hangzhoutongzhi.com/&quot;" useragent="Mozilla/4.0 (compatible; MSIE 6.0; Windows NT 5.1)"/>
<marker lat="23.1166992188" lng="113.25" city="Guangzhou" region="Guangdong" country="China" postal="None" date="16/Mar/2012:12:42:40 +0000" request="GET /stylesheets/skeleton.css HTTP/1.1" referer="&quot;http://www.hangzhoutongzhi.com/&quot;" useragent="Mozilla/4.0 (compatible; MSIE 6.0; Windows NT 5.1)"/>
<marker lat="32.7515983582" lng="-96.7646026611" city="Dallas" region="Texas" country="United States" postal="75215" date="16/Mar/2012:15:46:37 +0000" request="GET / HTTP/1.1" referer="&quot;http://www.kickstarter.com/projects/1650920829/nimbus&quot;" useragent="Mozilla/5.0 (Macintosh; Intel Mac OS X 10_7_3) AppleWebKit/535.11 (KHTML, like Gecko) Chrome/17.0.963.79 Safari/535.11"/>
<marker lat="43.0385017395" lng="-78.7642974854" city="Buffalo" region="New York" country="United States" postal="14228" date="16/Mar/2012:16:53:00 +0000" request="GET / HTTP/1.1" referer="&quot;http://www.kickstarter.com/projects/1650920829/nimbus&quot;" useragent="Mozilla/5.0 (Windows NT 6.1; WOW64) AppleWebKit/535.19 (KHTML, like Gecko) Chrome/18.0.1025.58 Safari/535.19"/>
<marker lat="38.0" lng="-97.0" city="None" region="None" country="United States" postal="None" date="16/Mar/2012:16:53:50 +0000" request="GET /resume.html HTTP/1.1" referer="&quot;http://search.yahoo.com/search?n=100&amp;ei=UTF-8&amp;va_vt=any&amp;vo_vt=any&amp;ve_vt=any&amp;vp_vt=any&amp;vd=y&amp;vst=0&amp;vf=all&amp;vc=us&amp;vm=r&amp;fl=1&amp;vl=lang_en&amp;fr=ush-&amp;p=%22resume.html%22+%22Intel+Corporation%22+-sample+-example+-template+-job+-SUBMIT+-Applicant++Data+development+-recruiter&amp;vs=&quot;" useragent="Mozilla/4.0 (compatible; MSIE 8.0; Windows NT 6.1; SV1; .NET CLR 2.0.50727)"/>
<marker lat="51.0" lng="9.0" city="None" region="None" country="Germany" postal="None" date="16/Mar/2012:20:23:04 +0000" request="GET / HTTP/1.1" referer="&quot;-&quot;" useragent="Mozilla/4.0 (compatible; MSIE 6.0; Windows 98; Win 9x4.90)"/>
<marker lat="1.54999995232" lng="110.333297729" city="Kuching" region="Sarawak" country="Malaysia" postal="None" date="16/Mar/2012:21:00:07 +0000" request="GET / HTTP/1.1" referer="&quot;-&quot;" useragent="Mozilla/5.0 (Macintosh; Intel Mac OS X 10_6_8) AppleWebKit/534.54.16 (KHTML, like Gecko) Version/5.1.4 Safari/534.54.16"/>
<marker lat="41.5584983826" lng="-73.0330963135" city="Waterbury" region="Connecticut" country="United States" postal="None" date="16/Mar/2012:21:05:43 +0000" request="GET / HTTP/1.1" referer="&quot;http://www.kickstarter.com/projects/1650920829/nimbus&quot;" useragent="Mozilla/5.0 (Windows NT 6.1; WOW64) AppleWebKit/535.11 (KHTML, like Gecko) Chrome/17.0.963.79 Safari/535.11"/>
<marker lat="45.5666999817" lng="8.93330001831" city="Canegrate" region="Lombardia" country="Italy" postal="None" date="16/Mar/2012:21:44:37 +0000" request="GET / HTTP/1.1" referer="&quot;http://www.kickstarter.com/projects/1650920829/nimbus&quot;" useragent="Mozilla/5.0 (iPhone; CPU iPhone OS 5_0_1 like Mac OS X) AppleWebKit/534.46 (KHTML, like Gecko) Version/5.1 Mobile/9A405 Safari/7534.48.3"/>
<marker lat="51.0" lng="9.0" city="None" region="None" country="Germany" postal="None" date="16/Mar/2012:21:52:49 +0000" request="GET / HTTP/1.1" referer="&quot;-&quot;" useragent="Mozilla/4.0 (compatible; MSIE 6.0; Windows 98; Win 9x4.90)"/>
<marker lat="37.5663986206" lng="126.999702454" city="Seoul" region="Seoul-t'ukpyolsi" country="Korea, Republic of" postal="None" date="16/Mar/2012:21:54:27 +0000" request="GET HTTP/1.1 HTTP/1.1" referer="&quot;-&quot;" useragent="Mozilla/5.0 (Windows NT 6.1) AppleWebKit/535.1 (KHTML, like Gecko) Chrome/13.0.782.220 Safari/535.1"/>
<marker lat="37.5663986206" lng="126.999702454" city="Seoul" region="Seoul-t'ukpyolsi" country="Korea, Republic of" postal="None" date="16/Mar/2012:21:54:39 +0000" request="GET HTTP/1.1&quot; 40" referer="&quot;-&quot;" useragent=""/>
<marker lat="40.154499054" lng="-75.380897522" city="Norristown" region="Pennsylvania" country="United States" postal="19403" date="16/Mar/2012:22:19:59 +0000" request="GET / HTTP/1.1" referer="&quot;-&quot;" useragent="Mozilla/4.0 (compatible; MSIE 5.5; Windows 98)"/>
<marker lat="-27.5" lng="153.016693115" city="Brisbane" region="Queensland" country="Australia" postal="None" date="16/Mar/2012:23:31:56 +0000" request="GET / HTTP/1.1" referer="&quot;http://www.kickstarter.com/projects/1650920829/nimbus?ref=card&quot;" useragent="Mozilla/5.0 (Windows NT 5.1; rv:11.0) Gecko/20100101 Firefox/11.0"/>
<marker lat="38.0" lng="-97.0" city="None" region="None" country="United States" postal="None" date="17/Mar/2012:01:45:54 +0000" request="GET /resume.html HTTP/1.1" referer="&quot;http://search.yahoo.com/search?n=100&amp;ei=UTF-8&amp;va_vt=any&amp;vo_vt=any&amp;ve_vt=any&amp;vp_vt=any&amp;vd=y&amp;vst=0&amp;vf=all&amp;vc=us&amp;vm=r&amp;fl=1&amp;vl=lang_en&amp;fr=ush-&amp;p=%22resume.html%22+%22Intel+Corporation%22+-sample+-example+-template+-job+-SUBMIT+-Applicant++java&amp;vs=&quot;" useragent="Mozilla/4.0 (compatible; MSIE 8.0; Windows NT 6.1; SV1; .NET CLR 2.0.50727)"/>
<marker lat="40.792098999" lng="-74.1626968384" city="Belleville" region="New Jersey" country="United States" postal="07109" date="17/Mar/2012:01:46:16 +0000" request="GET /resume.html HTTP/1.1" referer="&quot;http://search.yahoo.com/search?n=100&amp;ei=UTF-8&amp;va_vt=any&amp;vo_vt=any&amp;ve_vt=any&amp;vp_vt=any&amp;vd=m3&amp;vst=0&amp;vf=all&amp;vc=us&amp;vm=r&amp;fl=1&amp;vl=lang_en&amp;fr=ush-&amp;p=%22resume.html%22+%22Intel+Corporation%22+-sample+-example+-template+-job+-SUBMIT+-Applicant+JAVA&amp;vs=&quot;" useragent="Mozilla/4.0 (compatible; MSIE 8.0; Windows NT 6.1; SV1; .NET CLR 2.0.50727)"/>
<marker lat="38.2318000793" lng="-122.561798096" city="Petaluma" region="California" country="United States" postal="94954" date="17/Mar/2012:03:11:06 +0000" request="GET / HTTP/1.1" referer="&quot;http://www.kickstarter.com/projects/1650920829/nimbus?ref=card&quot;" useragent="Mozilla/5.0 (Windows NT 6.1; WOW64; rv:10.0.2) Gecko/20100101 Firefox/10.0.2"/>
<marker lat="40.792098999" lng="-74.1626968384" city="Belleville" region="New Jersey" country="United States" postal="07109" date="17/Mar/2012:03:54:36 +0000" request="GET /resume.html HTTP/1.1" referer="&quot;http://search.yahoo.com/search?n=100&amp;ei=UTF-8&amp;va_vt=any&amp;vo_vt=any&amp;ve_vt=any&amp;vp_vt=any&amp;vd=m3&amp;vst=0&amp;vf=all&amp;vc=us&amp;vm=r&amp;fl=1&amp;vl=lang_en&amp;fr=ush-&amp;p=%22resume.html%22+%22Intel+Corporation%22+-sample+-example+-template+-job+-SUBMIT+-Applicant+java&amp;vs=&quot;" useragent="Mozilla/4.0 (compatible; MSIE 8.0; Windows NT 6.1; SV1; .NET CLR 2.0.50727)"/>
<marker lat="38.7462005615" lng="-77.4903030396" city="Manassas" region="Virginia" country="United States" postal="20110" date="17/Mar/2012:04:06:53 +0000" request="GET / HTTP/1.1" referer="&quot;http://www.kickstarter.com/projects/1650920829/nimbus&quot;" useragent="Mozilla/5.0 (Windows NT 6.1) AppleWebKit/535.11 (KHTML, like Gecko) Chrome/17.0.963.79 Safari/535.11"/>
<marker lat="36.4986991882" lng="-119.279701233" city="Cutler" region="California" country="United States" postal="93615" date="17/Mar/2012:04:51:42 +0000" request="GET / HTTP/1.1" referer="&quot;-&quot;" useragent="Mozilla/5.0 (Macintosh; Intel Mac OS X 10_7_3) AppleWebKit/535.19 (KHTML, like Gecko) Chrome/18.0.1025.100 Safari/535.19"/>
<marker lat="34.2346000671" lng="-118.519302368" city="Northridge" region="California" country="United States" postal="91325" date="17/Mar/2012:05:49:13 +0000" request="GET / HTTP/1.1" referer="&quot;-&quot;" useragent="Mozilla/5.0 (Macintosh; Intel Mac OS X 10_7_2) AppleWebKit/534.52.7 (KHTML, like Gecko) Version/5.1.2 Safari/534.52.7"/>
<marker lat="38.935798645" lng="-77.1621017456" city="Mclean" region="Virginia" country="United States" postal="22101" date="17/Mar/2012:06:07:05 +0000" request="GET / HTTP/1.1" referer="&quot;http://www.kickstarter.com/projects/1650920829/nimbus?ref=card&quot;" useragent="Mozilla/5.0 (iPhone; CPU iPhone OS 5_1 like Mac OS X) AppleWebKit/534.46 (KHTML, like Gecko) Version/5.1 Mobile/9B179 Safari/7534.48.3"/>
<marker lat="39.9289016724" lng="116.388298035" city="Beijing" region="Beijing" country="China" postal="None" date="17/Mar/2012:06:12:39 +0000" request="GET / HTTP/1.1" referer="&quot;-&quot;" useragent="Mozilla/4.0 (compatible; MSIE 6.0; Windows NT 5.1)"/>
<marker lat="38.0" lng="-97.0" city="None" region="None" country="United States" postal="None" date="17/Mar/2012:06:36:36 +0000" request="GET / HTTP/1.1" referer="&quot;-&quot;" useragent="-"/>
<marker lat="36.4986991882" lng="-119.279701233" city="Cutler" region="California" country="United States" postal="93615" date="17/Mar/2012:06:47:55 +0000" request="GET /particles.html HTTP/1.1" referer="&quot;-&quot;" useragent="Mozilla/5.0 (Macintosh; Intel Mac OS X 10_7_3) AppleWebKit/535.19 (KHTML, like Gecko) Chrome/18.0.1025.100 Safari/535.19"/>
<marker lat="36.4986991882" lng="-119.279701233" city="Cutler" region="California" country="United States" postal="93615" date="17/Mar/2012:06:48:03 +0000" request="GET /particles.html HTTP/1.1" referer="&quot;-&quot;" useragent="Mozilla/5.0 (Macintosh; Intel Mac OS X 10_7_3) AppleWebKit/535.19 (KHTML, like Gecko) Chrome/18.0.1025.100 Safari/535.19"/>
<marker lat="38.0" lng="-97.0" city="None" region="None" country="United States" postal="None" date="17/Mar/2012:06:50:58 +0000" request="HEAD /particles.html HTTP/1.1" referer="&quot;-&quot;" useragent="UnwindFetchor/1.0 (+http://www.gnip.com/)"/>
<marker lat="38.0" lng="-97.0" city="None" region="None" country="United States" postal="None" date="17/Mar/2012:06:50:58 +0000" request="HEAD /particles.html HTTP/1.1" referer="&quot;-&quot;" useragent="UnwindFetchor/1.0 (+http://www.gnip.com/)"/>
<marker lat="38.0" lng="-97.0" city="None" region="None" country="United States" postal="None" date="17/Mar/2012:06:50:58 +0000" request="GET /particles.html HTTP/1.1" referer="&quot;-&quot;" useragent="RockMeltEmbedService"/>
<marker lat="38.0" lng="-97.0" city="None" region="None" country="United States" postal="None" date="17/Mar/2012:06:51:01 +0000" request="GET /particles.html HTTP/1.1" referer="&quot;-&quot;" useragent="Mozilla/4.0 (compatible; MSIE 7.0; Windows NT 6.0)"/>
<marker lat="38.0" lng="-97.0" city="None" region="None" country="United States" postal="None" date="17/Mar/2012:06:51:03 +0000" request="GET /particles.html HTTP/1.1" referer="&quot;-&quot;" useragent="Voyager/1.0"/>
<marker lat="38.0" lng="-97.0" city="None" region="None" country="United States" postal="None" date="17/Mar/2012:06:51:52 +0000" request="GET /particles.html HTTP/1.0" referer="&quot;-&quot;" useragent="Mozilla/5.0 (compatible; Butterfly/1.0; +http://labs.topsy.com/butterfly/) Gecko/2009032608 Firefox/3.0.8"/>
<marker lat="38.0" lng="-97.0" city="None" region="None" country="United States" postal="None" date="17/Mar/2012:06:51:53 +0000" request="GET /particles.html HTTP/1.0" referer="&quot;-&quot;" useragent="Mozilla/5.0 (compatible; Butterfly/1.0; +http://labs.topsy.com/butterfly/) Gecko/2009032608 Firefox/3.0.8"/>
<marker lat="36.4986991882" lng="-119.279701233" city="Cutler" region="California" country="United States" postal="93615" date="17/Mar/2012:07:02:11 +0000" request="GET /particles.html HTTP/1.1" referer="&quot;http://t.co/GznotC8I&quot;" useragent="Mozilla/5.0 (Macintosh; Intel Mac OS X 10_7_3) AppleWebKit/535.19 (KHTML, like Gecko) Chrome/18.0.1025.100 Safari/535.19"/>
<marker lat="38.0" lng="-97.0" city="None" region="None" country="United States" postal="None" date="17/Mar/2012:07:10:52 +0000" request="GET /particles.html HTTP/1.1" referer="&quot;-&quot;" useragent="Mozilla/5.0 (Macintosh; U; Intel Mac OS X 10.6; en-US; rv:1.9.2) Gecko/20100115 Firefox/3.6 (FlipboardProxy/1.1; +http://flipboard.com/browserproxy)"/>
<marker lat="36.4986991882" lng="-119.279701233" city="Cutler" region="California" country="United States" postal="93615" date="17/Mar/2012:07:42:01 +0000" request="GET /particles.html HTTP/1.1" referer="&quot;http://t.co/GznotC8I&quot;" useragent="Mozilla/5.0 (Macintosh; Intel Mac OS X 10_7_3) AppleWebKit/535.19 (KHTML, like Gecko) Chrome/18.0.1025.100 Safari/535.19"/>
<marker lat="33.698299408" lng="-117.357902527" city="Lake Elsinore" region="California" country="United States" postal="None" date="17/Mar/2012:08:28:13 +0000" request="GET /particles.html HTTP/1.1" referer="&quot;http://t.co/GznotC8I&quot;" useragent="Mozilla/5.0 (Macintosh; Intel Mac OS X 10_7_3) AppleWebKit/535.11 (KHTML, like Gecko) Chrome/17.0.963.79 Safari/535.11"/>
<marker lat="36.4986991882" lng="-119.279701233" city="Cutler" region="California" country="United States" postal="93615" date="17/Mar/2012:09:33:42 +0000" request="GET /particles.html HTTP/1.1" referer="&quot;https://twitter.com/sagargp/status/180908903872208896&quot;" useragent="Mozilla/5.0 (iPad; CPU OS 5_0_1 like Mac OS X) AppleWebKit/534.46 (KHTML, like Gecko) Mobile/9A405 Twitter for iPad"/>
<marker lat="23.1166992188" lng="113.25" city="Guangzhou" region="Guangdong" country="China" postal="None" date="17/Mar/2012:12:16:20 +0000" request="GET / HTTP/1.1" referer="&quot;-&quot;" useragent="Mozilla/4.0 (compatible; MSIE 6.0; Windows NT 5.1)"/>
<marker lat="23.1166992188" lng="113.25" city="Guangzhou" region="Guangdong" country="China" postal="None" date="17/Mar/2012:12:16:30 +0000" request="GET /stylesheets/skeleton.css HTTP/1.1" referer="&quot;http://www.semjy.com/&quot;" useragent="Mozilla/4.0 (compatible; MSIE 6.0; Windows NT 5.1)"/>
<marker lat="23.1166992188" lng="113.25" city="Guangzhou" region="Guangdong" country="China" postal="None" date="17/Mar/2012:12:16:30 +0000" request="GET /stylesheets/custom.css HTTP/1.1" referer="&quot;http://www.semjy.com/&quot;" useragent="Mozilla/4.0 (compatible; MSIE 6.0; Windows NT 5.1)"/>
<marker lat="23.1166992188" lng="113.25" city="Guangzhou" region="Guangdong" country="China" postal="None" date="17/Mar/2012:12:16:30 +0000" request="GET /javascripts/tabs.js HTTP/1.1" referer="&quot;http://www.semjy.com/&quot;" useragent="Mozilla/4.0 (compatible; MSIE 6.0; Windows NT 5.1)"/>
<marker lat="33.5589981079" lng="-112.431999207" city="Waddell" region="Arizona" country="United States" postal="85355" date="17/Mar/2012:13:53:34 +0000" request="GET / HTTP/1.1" referer="&quot;http://www.kickstarter.com/projects/1650920829/nimbus&quot;" useragent="Mozilla/5.0 (compatible; MSIE 9.0; Windows NT 6.1; WOW64; Trident/5.0; BOIE9;ENUS)"/>
<marker lat="38.0" lng="-97.0" city="None" region="None" country="United States" postal="None" date="17/Mar/2012:13:53:49 +0000" request="GET / HTTP/1.1" referer="&quot;-&quot;" useragent="Feedfetcher-Google; (+http://www.google.com/feedfetcher.html; feed-id=6385936691887397496)"/>
<marker lat="4.59999990463" lng="-74.0832977295" city="Bogot" region="Cundinamarca" country="Colombia" postal="None" date="17/Mar/2012:17:06:09 +0000" request="GET admin/scripts/setup.php HTTP/1.1" referer="&quot;-&quot;" useragent="ZmEu"/>
<marker lat="4.59999990463" lng="-74.0832977295" city="Bogot" region="Cundinamarca" country="Colombia" postal="None" date="17/Mar/2012:17:06:31 +0000" request="GET HTTP/1.1&quot; 40" referer="&quot;-&quot;" useragent=""/>
<marker lat="37.3842010498" lng="-122.019599915" city="Sunnyvale" region="California" country="United States" postal="None" date="17/Mar/2012:18:22:50 +0000" request="GET /particles.html HTTP/1.1" referer="&quot;http://t.co/GznotC8I&quot;" useragent="Mozilla/5.0 (Macintosh; Intel Mac OS X 10_7_3) AppleWebKit/535.11 (KHTML, like Gecko) Chrome/17.0.963.79 Safari/535.11"/>
<marker lat="33.8403015137" lng="-118.353897095" city="Torrance" region="California" country="United States" postal="90503" date="17/Mar/2012:19:14:34 +0000" request="GET / HTTP/1.0" referer="&quot;-&quot;" useragent="Mozilla/Nutch-1.2 (Windows; U; Windows NT 5.1; en-US; rv:1.9.1.11)"/>
<marker lat="40.2612991333" lng="-111.627098083" city="Provo" region="Utah" country="United States" postal="None" date="17/Mar/2012:21:39:13 +0000" request="GET /particles.html HTTP/1.1" referer="&quot;https://twitter.com/sagargp/status/180908903872208896&quot;" useragent="Mozilla/5.0 (iPod; U; CPU iPhone OS 4_2_1 like Mac OS X; pt-br) AppleWebKit/533.17.9 (KHTML, like Gecko) Mobile/8C148 Twitter for iPhone"/>
<marker lat="36.4986991882" lng="-119.279701233" city="Cutler" region="California" country="United States" postal="93615" date="17/Mar/2012:22:40:31 +0000" request="GET / HTTP/1.1" referer="&quot;-&quot;" useragent="Mozilla/5.0 (Macintosh; Intel Mac OS X 10_7_3) AppleWebKit/535.19 (KHTML, like Gecko) Chrome/18.0.1025.100 Safari/535.19"/>
<marker lat="34.0415992737" lng="-118.298797607" city="Los Angeles" region="California" country="United States" postal="None" date="17/Mar/2012:23:22:17 +0000" request="GET / HTTP/1.1" referer="&quot;-&quot;" useragent="Mozilla/5.0 (Macintosh; Intel Mac OS X 10_7_3) AppleWebKit/535.19 (KHTML, like Gecko) Chrome/18.0.1025.54 Safari/535.19"/>
</markers>
